{"input": {"tables_path": "/home/george/Documents/code/vkr/rustbench/tables-qa/set/ErgastF1/2/csv", "question_path": "/home/george/Documents/code/vkr/rustbench/tables-qa/set/ErgastF1/2/QA_english.json"}, "answers": "{\"answer\": 6}", "contexts": {"1-hop": "Table: constructors - 23 rows | Row 4: found via nationality | Row 5: found via nationality | Row 17: found via nationality | Row 21: found via nationality | Row 27: found via nationality | Row 34: found via nationality | Row 35: found via nationality | Row 37: found via nationality | Row 39: found via nationality | Row 41: found via nationality | Row 42: found via nationality | Row 43: found via nationality | Row 45: found via nationality | Row 49: found via nationality | Row 52: found via nationality | Row 58: found via nationality | Row 61: found via nationality | Row 62: found via nationality | Row 64: found via nationality | Row 65: found via nationality | Row 69: found via nationality | Row 70: found via nationality | Row 71: found via nationality\n|    |   constructorid | constructorref       | name                 | nationality   | url                                                         |\n|---:|----------------:|:---------------------|:---------------------|:--------------|:------------------------------------------------------------|\n|  4 |               5 | toro_rosso           | Toro Rosso           | Italian       | http://en.wikipedia.org/wiki/Scuderia_Toro_Rosso            |\n|  5 |               6 | ferrari              | Ferrari              | Italian       | http://en.wikipedia.org/wiki/Scuderia_Ferrari               |\n| 17 |              18 | minardi              | Minardi              | Italian       | http://en.wikipedia.org/wiki/Minardi                        |\n| 21 |              22 | benetton             | Benetton             | Italian       | http://en.wikipedia.org/wiki/Benetton_Formula               |\n| 27 |              28 | forti                | Forti                | Italian       | http://en.wikipedia.org/wiki/Forti                          |\n| 34 |              35 | dallara              | Dallara              | Italian       | http://en.wikipedia.org/wiki/Dallara                        |\n| 35 |              36 | fondmetal            | Fondmetal            | Italian       | http://en.wikipedia.org/wiki/Fondmetal                      |\n| 37 |              38 | moda                 | Andrea Moda          | Italian       | http://en.wikipedia.org/wiki/Andrea_Moda_Formula            |\n| 39 |              40 | lambo                | Lambo                | Italian       | http://en.wikipedia.org/wiki/Modena_(racing_team)           |\n| 41 |              42 | coloni               | Coloni               | Italian       | http://en.wikipedia.org/wiki/Enzo_Coloni_Racing_Car_Systems |\n| 42 |              44 | eurobrun             | Euro Brun            | Italian       | http://en.wikipedia.org/wiki/Euro_Brun                      |\n| 43 |              45 | osella               | Osella               | Italian       | http://en.wikipedia.org/wiki/Osella                         |\n| 45 |              47 | life                 | Life                 | Italian       | http://en.wikipedia.org/wiki/Life_(Racing_Team)             |\n| 49 |              51 | alfa                 | Alfa Romeo           | Italian       | http://en.wikipedia.org/wiki/Alfa_Romeo_(Formula_One)       |\n| 52 |              54 | ats                  | ATS                  | Italian       | http://en.wikipedia.org/wiki/ATS_(wheels)                   |\n| 58 |              60 | merzario             | Merzario             | Italian       | http://en.wikipedia.org/wiki/Merzario                       |\n| 61 |              81 | tecno                | Tecno                | Italian       | http://en.wikipedia.org/wiki/Tecno                          |\n| 62 |              86 | tomaso               | De Tomaso            | Italian       | http://en.wikipedia.org/wiki/De_Tomaso                      |\n| 64 |             104 | behra-porsche        | Behra-Porsche        | Italian       | http://en.wikipedia.org/wiki/Behra-Porsche                  |\n| 65 |             105 | maserati             | Maserati             | Italian       | http://en.wikipedia.org/wiki/Maserati                       |\n| 69 |             174 | de_tomaso-osca       | De Tomaso-Osca       | Italian       | http://en.wikipedia.org/wiki/De_Tomaso                      |\n| 70 |             175 | de_tomaso-alfa_romeo | De Tomaso-Alfa Romeo | Italian       | http://en.wikipedia.org/wiki/De_Tomaso                      |\n| 71 |             179 | de_tomaso-ferrari    | De Tomaso-Ferrari    | Italian       | http://en.wikipedia.org/wiki/De_Tomaso                      |\n\nTable: circuits - 3 rows | Row 13: found via country | Row 20: found via country | Row 64: found via country\n|    |   circuitid | circuitref   | name                          | location   | country   |     lat |      lng |   alt | url                                                        |\n|---:|------------:|:-------------|:------------------------------|:-----------|:----------|--------:|---------:|------:|:-----------------------------------------------------------|\n| 13 |          14 | monza        | Autodromo Nazionale di Monza  | Monza      | Italy     | 45.6156 |  9.28111 |   nan | http://en.wikipedia.org/wiki/Autodromo_Nazionale_Monza     |\n| 20 |          21 | imola        | Autodromo Enzo e Dino Ferrari | Imola      | Italy     | 44.3439 | 11.7167  |   nan | http://en.wikipedia.org/wiki/Autodromo_Enzo_e_Dino_Ferrari |\n| 64 |          65 | pescara      | Pescara Circuit               | Pescara    | Italy     | 42.475  | 14.1508  |   nan | http://en.wikipedia.org/wiki/Pescara_Circuit               |", "2-hop": "Table: constructors - 23 rows | Row 4: found via constructorid, nationality | Row 5: found via constructorid, nationality | Row 17: found via constructorid, nationality | Row 21: found via constructorid, nationality | Row 27: found via constructorid, nationality | Row 34: found via constructorid, nationality | Row 35: found via constructorid, nationality | Row 37: found via constructorid, nationality | Row 39: found via constructorid, nationality | Row 41: found via constructorid, nationality | Row 42: found via constructorid, nationality | Row 43: found via constructorid, nationality | Row 45: found via constructorid, nationality | Row 49: found via constructorid, nationality | Row 52: found via constructorid, nationality | Row 58: found via constructorid, nationality | Row 61: found via constructorid, nationality | Row 62: found via constructorid, nationality | Row 64: found via constructorid, nationality | Row 65: found via constructorid, nationality | Row 69: found via constructorid, nationality | Row 70: found via constructorid, nationality | Row 71: found via constructorid, nationality\n|    |   constructorid | constructorref       | name                 | nationality   | url                                                         |\n|---:|----------------:|:---------------------|:---------------------|:--------------|:------------------------------------------------------------|\n|  4 |               5 | toro_rosso           | Toro Rosso           | Italian       | http://en.wikipedia.org/wiki/Scuderia_Toro_Rosso            |\n|  5 |               6 | ferrari              | Ferrari              | Italian       | http://en.wikipedia.org/wiki/Scuderia_Ferrari               |\n| 17 |              18 | minardi              | Minardi              | Italian       | http://en.wikipedia.org/wiki/Minardi                        |\n| 21 |              22 | benetton             | Benetton             | Italian       | http://en.wikipedia.org/wiki/Benetton_Formula               |\n| 27 |              28 | forti                | Forti                | Italian       | http://en.wikipedia.org/wiki/Forti                          |\n| 34 |              35 | dallara              | Dallara              | Italian       | http://en.wikipedia.org/wiki/Dallara                        |\n| 35 |              36 | fondmetal            | Fondmetal            | Italian       | http://en.wikipedia.org/wiki/Fondmetal                      |\n| 37 |              38 | moda                 | Andrea Moda          | Italian       | http://en.wikipedia.org/wiki/Andrea_Moda_Formula            |\n| 39 |              40 | lambo                | Lambo                | Italian       | http://en.wikipedia.org/wiki/Modena_(racing_team)           |\n| 41 |              42 | coloni               | Coloni               | Italian       | http://en.wikipedia.org/wiki/Enzo_Coloni_Racing_Car_Systems |\n| 42 |              44 | eurobrun             | Euro Brun            | Italian       | http://en.wikipedia.org/wiki/Euro_Brun                      |\n| 43 |              45 | osella               | Osella               | Italian       | http://en.wikipedia.org/wiki/Osella                         |\n| 45 |              47 | life                 | Life                 | Italian       | http://en.wikipedia.org/wiki/Life_(Racing_Team)             |\n| 49 |              51 | alfa                 | Alfa Romeo           | Italian       | http://en.wikipedia.org/wiki/Alfa_Romeo_(Formula_One)       |\n| 52 |              54 | ats                  | ATS                  | Italian       | http://en.wikipedia.org/wiki/ATS_(wheels)                   |\n| 58 |              60 | merzario             | Merzario             | Italian       | http://en.wikipedia.org/wiki/Merzario                       |\n| 61 |              81 | tecno                | Tecno                | Italian       | http://en.wikipedia.org/wiki/Tecno                          |\n| 62 |              86 | tomaso               | De Tomaso            | Italian       | http://en.wikipedia.org/wiki/De_Tomaso                      |\n| 64 |             104 | behra-porsche        | Behra-Porsche        | Italian       | http://en.wikipedia.org/wiki/Behra-Porsche                  |\n| 65 |             105 | maserati             | Maserati             | Italian       | http://en.wikipedia.org/wiki/Maserati                       |\n| 69 |             174 | de_tomaso-osca       | De Tomaso-Osca       | Italian       | http://en.wikipedia.org/wiki/De_Tomaso                      |\n| 70 |             175 | de_tomaso-alfa_romeo | De Tomaso-Alfa Romeo | Italian       | http://en.wikipedia.org/wiki/De_Tomaso                      |\n| 71 |             179 | de_tomaso-ferrari    | De Tomaso-Ferrari    | Italian       | http://en.wikipedia.org/wiki/De_Tomaso                      |\n\nTable: circuits - 3 rows | Row 13: found via circuitid, country | Row 20: found via circuitid, country | Row 64: found via circuitid, country\n|    |   circuitid | circuitref   | name                          | location   | country   |     lat |      lng |   alt | url                                                        |\n|---:|------------:|:-------------|:------------------------------|:-----------|:----------|--------:|---------:|------:|:-----------------------------------------------------------|\n| 13 |          14 | monza        | Autodromo Nazionale di Monza  | Monza      | Italy     | 45.6156 |  9.28111 |   nan | http://en.wikipedia.org/wiki/Autodromo_Nazionale_Monza     |\n| 20 |          21 | imola        | Autodromo Enzo e Dino Ferrari | Imola      | Italy     | 44.3439 | 11.7167  |   nan | http://en.wikipedia.org/wiki/Autodromo_Enzo_e_Dino_Ferrari |\n| 64 |          65 | pescara      | Pescara Circuit               | Pescara    | Italy     | 42.475  | 14.1508  |   nan | http://en.wikipedia.org/wiki/Pescara_Circuit               |", "3-hop": "Table: constructors - 74 rows | Row 0: found via nationality | Row 1: found via nationality | Row 2: found via nationality | Row 3: found via nationality | Row 4: found via constructorid, nationality | Row 5: found via constructorid, nationality | Row 6: found via nationality | Row 7: found via nationality | Row 8: found via nationality | Row 9: found via nationality | Row 10: found via nationality | Row 11: found via nationality | Row 12: found via nationality | Row 13: found via nationality | Row 14: found via nationality | Row 15: found via nationality | Row 16: found via nationality | Row 17: found via constructorid, nationality | Row 18: found via nationality | Row 19: found via nationality | Row 20: found via nationality | Row 21: found via constructorid, nationality | Row 22: found via nationality | Row 23: found via nationality | Row 24: found via nationality | Row 25: found via nationality | Row 26: found via nationality | Row 27: found via constructorid, nationality | Row 28: found via nationality | Row 29: found via nationality | Row 30: found via nationality | Row 31: found via nationality | Row 32: found via nationality | Row 33: found via nationality | Row 34: found via constructorid, nationality | Row 35: found via constructorid, nationality | Row 36: found via nationality | Row 37: found via constructorid, nationality | Row 38: found via nationality | Row 39: found via constructorid, nationality | Row 40: found via nationality | Row 41: found via constructorid, nationality | Row 42: found via constructorid, nationality | Row 43: found via constructorid, nationality | Row 44: found via nationality | Row 45: found via constructorid, nationality | Row 46: found via nationality | Row 47: found via nationality | Row 48: found via nationality | Row 49: found via constructorid, nationality | Row 50: found via nationality | Row 51: found via nationality | Row 52: found via constructorid, nationality | Row 53: found via nationality | Row 54: found via nationality | Row 55: found via nationality | Row 56: found via nationality | Row 57: found via nationality | Row 58: found via constructorid, nationality | Row 59: found via nationality | Row 60: found via nationality | Row 61: found via constructorid, nationality | Row 62: found via constructorid, nationality | Row 63: found via nationality | Row 64: found via constructorid, nationality | Row 65: found via constructorid, nationality | Row 66: found via nationality | Row 67: found via nationality | Row 68: found via nationality | Row 69: found via constructorid, nationality | Row 70: found via constructorid, nationality | Row 71: found via constructorid, nationality | Row 72: found via nationality | Row 73: found via nationality\n|    |   constructorid | constructorref       | name                 | nationality   | url                                                               |\n|---:|----------------:|:---------------------|:---------------------|:--------------|:------------------------------------------------------------------|\n|  0 |               1 | mclaren              | McLaren              | British       | http://en.wikipedia.org/wiki/McLaren                              |\n|  1 |               2 | bmw_sauber           | BMW Sauber           | German        | http://en.wikipedia.org/wiki/BMW_Sauber                           |\n|  2 |               3 | williams             | Williams             | British       | http://en.wikipedia.org/wiki/Williams_Grand_Prix_Engineering      |\n|  3 |               4 | renault              | Renault              | French        | http://en.wikipedia.org/wiki/Renault_F1                           |\n|  4 |               5 | toro_rosso           | Toro Rosso           | Italian       | http://en.wikipedia.org/wiki/Scuderia_Toro_Rosso                  |\n|  5 |               6 | ferrari              | Ferrari              | Italian       | http://en.wikipedia.org/wiki/Scuderia_Ferrari                     |\n|  6 |               7 | toyota               | Toyota               | Japanese      | http://en.wikipedia.org/wiki/Toyota_Racing                        |\n|  7 |               8 | super_aguri          | Super Aguri          | Japanese      | http://en.wikipedia.org/wiki/Super_Aguri_F1                       |\n|  8 |               9 | red_bull             | Red Bull             | Austrian      | http://en.wikipedia.org/wiki/Red_Bull_Racing                      |\n|  9 |              10 | force_india          | Force India          | Indian        | http://en.wikipedia.org/wiki/Force_India                          |\n| 10 |              11 | honda                | Honda                | Japanese      | http://en.wikipedia.org/wiki/Honda_Racing_F1                      |\n| 11 |              12 | spyker               | Spyker               | Dutch         | http://en.wikipedia.org/wiki/Spyker_F1                            |\n| 12 |              13 | mf1                  | MF1                  | Russian       | http://en.wikipedia.org/wiki/Midland_F1_Racing                    |\n| 13 |              14 | spyker_mf1           | Spyker MF1           | Dutch         | http://en.wikipedia.org/wiki/Midland_F1_Racing                    |\n| 14 |              15 | sauber               | Sauber               | Swiss         | http://en.wikipedia.org/wiki/Sauber                               |\n| 15 |              16 | bar                  | BAR                  | British       | http://en.wikipedia.org/wiki/British_American_Racing              |\n| 16 |              17 | jordan               | Jordan               | Irish         | http://en.wikipedia.org/wiki/Jordan_Grand_Prix                    |\n| 17 |              18 | minardi              | Minardi              | Italian       | http://en.wikipedia.org/wiki/Minardi                              |\n| 18 |              19 | jaguar               | Jaguar               | British       | http://en.wikipedia.org/wiki/Jaguar_Racing                        |\n| 19 |              20 | prost                | Prost                | French        | http://en.wikipedia.org/wiki/Prost_Grand_Prix                     |\n| 20 |              21 | arrows               | Arrows               | British       | http://en.wikipedia.org/wiki/Arrows_Grand_Prix_International      |\n| 21 |              22 | benetton             | Benetton             | Italian       | http://en.wikipedia.org/wiki/Benetton_Formula                     |\n| 22 |              23 | brawn                | Brawn                | British       | http://en.wikipedia.org/wiki/Brawn_GP                             |\n| 23 |              24 | stewart              | Stewart              | British       | http://en.wikipedia.org/wiki/Stewart_Grand_Prix                   |\n| 24 |              25 | tyrrell              | Tyrrell              | British       | http://en.wikipedia.org/wiki/Tyrrell_Racing                       |\n| 25 |              26 | lola                 | Lola                 | British       | http://en.wikipedia.org/wiki/MasterCard_Lola                      |\n| 26 |              27 | ligier               | Ligier               | French        | http://en.wikipedia.org/wiki/Ligier                               |\n| 27 |              28 | forti                | Forti                | Italian       | http://en.wikipedia.org/wiki/Forti                                |\n| 28 |              29 | footwork             | Footwork             | British       | http://en.wikipedia.org/wiki/Footwork_Arrows                      |\n| 29 |              30 | pacific              | Pacific              | British       | http://en.wikipedia.org/wiki/Pacific_Racing                       |\n| 30 |              31 | simtek               | Simtek               | British       | http://en.wikipedia.org/wiki/Simtek                               |\n| 31 |              32 | team_lotus           | Team Lotus           | British       | http://en.wikipedia.org/wiki/Team_Lotus                           |\n| 32 |              33 | larrousse            | Larrousse            | French        | http://en.wikipedia.org/wiki/Larrousse                            |\n| 33 |              34 | brabham              | Brabham              | British       | http://en.wikipedia.org/wiki/Brabham                              |\n| 34 |              35 | dallara              | Dallara              | Italian       | http://en.wikipedia.org/wiki/Dallara                              |\n| 35 |              36 | fondmetal            | Fondmetal            | Italian       | http://en.wikipedia.org/wiki/Fondmetal                            |\n| 36 |              37 | march                | March                | British       | http://en.wikipedia.org/wiki/March_Engineering                    |\n| 37 |              38 | moda                 | Andrea Moda          | Italian       | http://en.wikipedia.org/wiki/Andrea_Moda_Formula                  |\n| 38 |              39 | ags                  | AGS                  | French        | http://en.wikipedia.org/wiki/Automobiles_Gonfaronnaises_Sportives |\n| 39 |              40 | lambo                | Lambo                | Italian       | http://en.wikipedia.org/wiki/Modena_(racing_team)                 |\n| 40 |              41 | leyton               | Leyton House         | British       | http://en.wikipedia.org/wiki/Leyton_House                         |\n| 41 |              42 | coloni               | Coloni               | Italian       | http://en.wikipedia.org/wiki/Enzo_Coloni_Racing_Car_Systems       |\n| 42 |              44 | eurobrun             | Euro Brun            | Italian       | http://en.wikipedia.org/wiki/Euro_Brun                            |\n| 43 |              45 | osella               | Osella               | Italian       | http://en.wikipedia.org/wiki/Osella                               |\n| 44 |              46 | onyx                 | Onyx                 | British       | http://en.wikipedia.org/wiki/Onyx_(racing_team)                   |\n| 45 |              47 | life                 | Life                 | Italian       | http://en.wikipedia.org/wiki/Life_(Racing_Team)                   |\n| 46 |              48 | rial                 | Rial                 | German        | http://en.wikipedia.org/wiki/Rial_%28racing_team%29               |\n| 47 |              49 | zakspeed             | Zakspeed             | German        | http://en.wikipedia.org/wiki/Zakspeed                             |\n| 48 |              50 | ram                  | RAM                  | British       | http://en.wikipedia.org/wiki/RAM_Racing                           |\n| 49 |              51 | alfa                 | Alfa Romeo           | Italian       | http://en.wikipedia.org/wiki/Alfa_Romeo_(Formula_One)             |\n| 50 |              52 | spirit               | Spirit               | British       | http://en.wikipedia.org/wiki/Spirit_(racing_team)                 |\n| 51 |              53 | toleman              | Toleman              | British       | http://en.wikipedia.org/wiki/Toleman                              |\n| 52 |              54 | ats                  | ATS                  | Italian       | http://en.wikipedia.org/wiki/ATS_(wheels)                         |\n| 53 |              55 | theodore             | Theodore             | Hong Kong     | http://en.wikipedia.org/wiki/Theodore_Racing                      |\n| 54 |              56 | fittipaldi           | Fittipaldi           | Brazilian     | http://en.wikipedia.org/wiki/Fittipaldi_%28constructor%29         |\n| 55 |              57 | ensign               | Ensign               | British       | http://en.wikipedia.org/wiki/Ensign_%28racing_team%29             |\n| 56 |              58 | shadow               | Shadow               | British       | http://en.wikipedia.org/wiki/Shadow_Racing_Cars                   |\n| 57 |              59 | wolf                 | Wolf                 | Canadian      | http://en.wikipedia.org/wiki/Walter_Wolf_Racing                   |\n| 58 |              60 | merzario             | Merzario             | Italian       | http://en.wikipedia.org/wiki/Merzario                             |\n| 59 |              61 | kauhsen              | Kauhsen              | German        | http://en.wikipedia.org/wiki/Kauhsen                              |\n| 60 |              66 | brm                  | BRM                  | British       | http://en.wikipedia.org/wiki/BRM                                  |\n| 61 |              81 | tecno                | Tecno                | Italian       | http://en.wikipedia.org/wiki/Tecno                                |\n| 62 |              86 | tomaso               | De Tomaso            | Italian       | http://en.wikipedia.org/wiki/De_Tomaso                            |\n| 63 |              87 | cooper               | Cooper               | British       | http://en.wikipedia.org/wiki/Cooper_Car_Company                   |\n| 64 |             104 | behra-porsche        | Behra-Porsche        | Italian       | http://en.wikipedia.org/wiki/Behra-Porsche                        |\n| 65 |             105 | maserati             | Maserati             | Italian       | http://en.wikipedia.org/wiki/Maserati                             |\n| 66 |             131 | mercedes             | Mercedes             | German        | http://en.wikipedia.org/wiki/Mercedes-Benz_in_Formula_One         |\n| 67 |             170 | cooper-climax        | Cooper-Climax        | British       | http://en.wikipedia.org/wiki/Cooper_Car_Company                   |\n| 68 |             172 | lotus-climax         | Lotus-Climax         | British       | http://en.wikipedia.org/wiki/Team_Lotus                           |\n| 69 |             174 | de_tomaso-osca       | De Tomaso-Osca       | Italian       | http://en.wikipedia.org/wiki/De_Tomaso                            |\n| 70 |             175 | de_tomaso-alfa_romeo | De Tomaso-Alfa Romeo | Italian       | http://en.wikipedia.org/wiki/De_Tomaso                            |\n| 71 |             179 | de_tomaso-ferrari    | De Tomaso-Ferrari    | Italian       | http://en.wikipedia.org/wiki/De_Tomaso                            |\n| 72 |             180 | lotus-ford           | Lotus-Ford           | British       | http://en.wikipedia.org/wiki/Team_Lotus                           |\n| 73 |             191 | brabham-repco        | Brabham-Repco        | British       | http://en.wikipedia.org/wiki/Brabham                              |\n\nTable: circuits - 73 rows | Row 0: found via country | Row 1: found via country | Row 2: found via country | Row 3: found via country | Row 4: found via country | Row 5: found via country | Row 6: found via country | Row 7: found via country | Row 8: found via country | Row 9: found via country | Row 10: found via country | Row 11: found via country | Row 12: found via country | Row 13: found via circuitid, country | Row 14: found via country | Row 15: found via country | Row 16: found via country | Row 17: found via country | Row 18: found via country | Row 19: found via country | Row 20: found via circuitid, country | Row 21: found via country | Row 22: found via country | Row 23: found via country | Row 24: found via country | Row 25: found via country | Row 26: found via country | Row 27: found via country | Row 28: found via country | Row 29: found via country | Row 30: found via country | Row 31: found via country | Row 32: found via country | Row 33: found via country | Row 34: found via country | Row 35: found via country | Row 36: found via country | Row 37: found via country | Row 38: found via country | Row 39: found via country | Row 40: found via country | Row 41: found via country | Row 42: found via country | Row 43: found via country | Row 44: found via country | Row 45: found via country | Row 46: found via country | Row 47: found via country | Row 48: found via country | Row 49: found via country | Row 50: found via country | Row 51: found via country | Row 52: found via country | Row 53: found via country | Row 54: found via country | Row 55: found via country | Row 56: found via country | Row 57: found via country | Row 58: found via country | Row 59: found via country | Row 60: found via country | Row 61: found via country | Row 62: found via country | Row 63: found via country | Row 64: found via circuitid, country | Row 65: found via country | Row 66: found via country | Row 67: found via country | Row 68: found via country | Row 69: found via country | Row 70: found via country | Row 71: found via country | Row 72: found via country\n|    |   circuitid | circuitref     | name                                  | location              | country      |       lat |         lng |   alt | url                                                                     |\n|---:|------------:|:---------------|:--------------------------------------|:----------------------|:-------------|----------:|------------:|------:|:------------------------------------------------------------------------|\n|  0 |           1 | albert_park    | Albert Park Grand Prix Circuit        | Melbourne             | Australia    | -37.8497  |  144.968    |    10 | http://en.wikipedia.org/wiki/Melbourne_Grand_Prix_Circuit               |\n|  1 |           2 | sepang         | Sepang International Circuit          | Kuala Lumpur          | Malaysia     |   2.76083 |  101.738    |   nan | http://en.wikipedia.org/wiki/Sepang_International_Circuit               |\n|  2 |           3 | bahrain        | Bahrain International Circuit         | Sakhir                | Bahrain      |  26.0325  |   50.5106   |   nan | http://en.wikipedia.org/wiki/Bahrain_International_Circuit              |\n|  3 |           4 | catalunya      | Circuit de Barcelona-Catalunya        | Montmeló              | Spain        |  41.57    |    2.26111  |   nan | http://en.wikipedia.org/wiki/Circuit_de_Barcelona-Catalunya             |\n|  4 |           5 | istanbul       | Istanbul Park                         | Istanbul              | Turkey       |  40.9517  |   29.405    |   nan | http://en.wikipedia.org/wiki/Istanbul_Park                              |\n|  5 |           6 | monaco         | Circuit de Monaco                     | Monte-Carlo           | Monaco       |  43.7347  |    7.42056  |   nan | http://en.wikipedia.org/wiki/Circuit_de_Monaco                          |\n|  6 |           7 | villeneuve     | Circuit Gilles Villeneuve             | Montreal              | Canada       |  45.5     |  -73.5228   |   nan | http://en.wikipedia.org/wiki/Circuit_Gilles_Villeneuve                  |\n|  7 |           8 | magny_cours    | Circuit de Nevers Magny-Cours         | Magny Cours           | France       |  46.8642  |    3.16361  |   nan | http://en.wikipedia.org/wiki/Circuit_de_Nevers_Magny-Cours              |\n|  8 |           9 | silverstone    | Silverstone Circuit                   | Silverstone           | UK           |  52.0786  |   -1.01694  |   nan | http://en.wikipedia.org/wiki/Silverstone_Circuit                        |\n|  9 |          10 | hockenheimring | Hockenheimring                        | Hockenheim            | Germany      |  49.3278  |    8.56583  |   nan | http://en.wikipedia.org/wiki/Hockenheimring                             |\n| 10 |          11 | hungaroring    | Hungaroring                           | Budapest              | Hungary      |  47.5789  |   19.2486   |   nan | http://en.wikipedia.org/wiki/Hungaroring                                |\n| 11 |          12 | valencia       | Valencia Street Circuit               | Valencia              | Spain        |  39.4589  |   -0.331667 |   nan | http://en.wikipedia.org/wiki/Valencia_Street_Circuit                    |\n| 12 |          13 | spa            | Circuit de Spa-Francorchamps          | Spa                   | Belgium      |  50.4372  |    5.97139  |   nan | http://en.wikipedia.org/wiki/Circuit_de_Spa-Francorchamps               |\n| 13 |          14 | monza          | Autodromo Nazionale di Monza          | Monza                 | Italy        |  45.6156  |    9.28111  |   nan | http://en.wikipedia.org/wiki/Autodromo_Nazionale_Monza                  |\n| 14 |          15 | marina_bay     | Marina Bay Street Circuit             | Marina Bay            | Singapore    |   1.2914  |  103.864    |   nan | http://en.wikipedia.org/wiki/Marina_Bay_Street_Circuit                  |\n| 15 |          16 | fuji           | Fuji Speedway                         | Oyama                 | Japan        |  35.3717  |  138.927    |   nan | http://en.wikipedia.org/wiki/Fuji_Speedway                              |\n| 16 |          17 | shanghai       | Shanghai International Circuit        | Shanghai              | China        |  31.3389  |  121.22     |   nan | http://en.wikipedia.org/wiki/Shanghai_International_Circuit             |\n| 17 |          18 | interlagos     | Autódromo José Carlos Pace            | São Paulo             | Brazil       | -23.7036  |  -46.6997   |   nan | http://en.wikipedia.org/wiki/Aut%C3%B3dromo_Jos%C3%A9_Carlos_Pace       |\n| 18 |          19 | indianapolis   | Indianapolis Motor Speedway           | Indianapolis          | USA          |  39.795   |  -86.2347   |   nan | http://en.wikipedia.org/wiki/Indianapolis_Motor_Speedway                |\n| 19 |          20 | nurburgring    | Nürburgring                           | Nürburg               | Germany      |  50.3356  |    6.9475   |   nan | http://en.wikipedia.org/wiki/N%C3%BCrburgring                           |\n| 20 |          21 | imola          | Autodromo Enzo e Dino Ferrari         | Imola                 | Italy        |  44.3439  |   11.7167   |   nan | http://en.wikipedia.org/wiki/Autodromo_Enzo_e_Dino_Ferrari              |\n| 21 |          22 | suzuka         | Suzuka Circuit                        | Suzuka                | Japan        |  34.8431  |  136.541    |   nan | http://en.wikipedia.org/wiki/Suzuka_Circuit                             |\n| 22 |          23 | osterreichring | A1-Ring                               | Spielburg             | Austria      |  47.2197  |   14.7647   |   nan | http://en.wikipedia.org/wiki/A1-Ring                                    |\n| 23 |          24 | yas_marina     | Yas Marina Circuit                    | Abu Dhabi             | UAE          |  24.4672  |   54.6031   |   nan | http://en.wikipedia.org/wiki/Yas_Marina_Circuit                         |\n| 24 |          25 | galvez         | Autódromo Juan y Oscar Gálvez         | Buenos Aires          | Argentina    | -34.6943  |  -58.4593   |   nan | http://en.wikipedia.org/wiki/Aut%C3%B3dromo_Oscar_Alfredo_G%C3%A1lvez   |\n| 25 |          26 | jerez          | Circuito de Jerez                     | Jerez de la Frontera  | Spain        |  36.7083  |   -6.03417  |   nan | http://en.wikipedia.org/wiki/Circuito_Permanente_de_Jerez               |\n| 26 |          27 | estoril        | Autódromo do Estoril                  | Estoril               | Portugal     |  38.7506  |   -9.39417  |   nan | http://en.wikipedia.org/wiki/Aut%C3%B3dromo_do_Estoril                  |\n| 27 |          28 | okayama        | Okayama International Circuit         | Okayama               | Japan        |  34.915   |  134.221    |   nan | http://en.wikipedia.org/wiki/TI_Circuit                                 |\n| 28 |          29 | adelaide       | Adelaide Street Circuit               | Adelaide              | Australia    | -34.9272  |  138.617    |   nan | http://en.wikipedia.org/wiki/Adelaide_Street_Circuit                    |\n| 29 |          30 | kyalami        | Kyalami                               | Midrand               | South Africa | -25.9894  |   28.0767   |   nan | http://en.wikipedia.org/wiki/Kyalami                                    |\n| 30 |          31 | donington      | Donington Park                        | Castle Donington      | UK           |  52.8306  |   -1.37528  |   nan | http://en.wikipedia.org/wiki/Donington_Park                             |\n| 31 |          32 | rodriguez      | Autódromo Hermanos Rodríguez          | Mexico City           | Mexico       |  19.4042  |  -99.0907   |   nan | http://en.wikipedia.org/wiki/Aut%C3%B3dromo_Hermanos_Rodr%C3%ADguez     |\n| 32 |          33 | phoenix        | Phoenix street circuit                | Phoenix               | USA          |  33.4479  | -112.075    |   nan | http://en.wikipedia.org/wiki/Phoenix_street_circuit                     |\n| 33 |          34 | ricard         | Circuit Paul Ricard                   | Le Castellet          | France       |  43.2506  |    5.79167  |   nan | http://en.wikipedia.org/wiki/Paul_Ricard_Circuit                        |\n| 34 |          35 | yeongam        | Korean International Circuit          | Yeongam County        | Korea        |  34.7333  |  126.417    |   nan | http://en.wikipedia.org/wiki/Korean_International_Circuit               |\n| 35 |          36 | jacarepagua    | Autódromo Internacional Nelson Piquet | Rio de Janeiro        | Brazil       | -22.9756  |  -43.395    |   nan | http://en.wikipedia.org/wiki/Aut%C3%B3dromo_Internacional_Nelson_Piquet |\n| 36 |          37 | detroit        | Detroit Street Circuit                | Detroit               | USA          |  42.3298  |  -83.0401   |   nan | http://en.wikipedia.org/wiki/Detroit_street_circuit                     |\n| 37 |          38 | brands_hatch   | Brands Hatch                          | Kent                  | UK           |  51.3569  |    0.263056 |   nan | http://en.wikipedia.org/wiki/Brands_Hatch                               |\n| 38 |          39 | zandvoort      | Circuit Park Zandvoort                | Zandvoort             | Netherlands  |  52.3888  |    4.54092  |   nan | http://en.wikipedia.org/wiki/Circuit_Zandvoort                          |\n| 39 |          40 | zolder         | Zolder                                | Heusden-Zolder        | Belgium      |  50.9894  |    5.25694  |   nan | http://en.wikipedia.org/wiki/Zolder                                     |\n| 40 |          41 | dijon          | Dijon-Prenois                         | Dijon                 | France       |  47.3625  |    4.89913  |   nan | http://en.wikipedia.org/wiki/Dijon-Prenois                              |\n| 41 |          42 | dallas         | Fair Park                             | Dallas                | USA          |  32.7774  |  -96.7587   |   nan | http://en.wikipedia.org/wiki/Fair_Park                                  |\n| 42 |          43 | long_beach     | Long Beach                            | California            | USA          |  33.7651  | -118.189    |   nan | http://en.wikipedia.org/wiki/Long_Beach,_California                     |\n| 43 |          44 | las_vegas      | Las Vegas Street Circuit              | Nevada                | USA          |  36.1162  | -115.174    |   nan | http://en.wikipedia.org/wiki/Las_Vegas,_Nevada                          |\n| 44 |          45 | jarama         | Jarama                                | Madrid                | Spain        |  40.6171  |   -3.58558  |   nan | http://en.wikipedia.org/wiki/Circuito_Permanente_Del_Jarama             |\n| 45 |          46 | watkins_glen   | Watkins Glen                          | New York State        | USA          |  42.3369  |  -76.9272   |   nan | http://en.wikipedia.org/wiki/Watkins_Glen_International                 |\n| 46 |          47 | anderstorp     | Scandinavian Raceway                  | Anderstorp            | Sweden       |  57.2653  |   13.6042   |   nan | http://en.wikipedia.org/wiki/Scandinavian_Raceway                       |\n| 47 |          48 | mosport        | Mosport International Raceway         | Ontario               | Canada       |  44.0481  |  -78.6756   |   nan | http://en.wikipedia.org/wiki/Mosport                                    |\n| 48 |          49 | montjuic       | Montjuïc                              | Barcelona             | Spain        |  41.3664  |    2.15167  |   nan | http://en.wikipedia.org/wiki/Montju%C3%AFc_circuit                      |\n| 49 |          50 | nivelles       | Nivelles-Baulers                      | Brussels              | Belgium      |  50.6211  |    4.32694  |   nan | http://en.wikipedia.org/wiki/Nivelles-Baulers                           |\n| 50 |          51 | charade        | Charade Circuit                       | Clermont-Ferrand      | France       |  45.7472  |    3.03889  |   nan | http://en.wikipedia.org/wiki/Charade_Circuit                            |\n| 51 |          52 | tremblant      | Circuit Mont-Tremblant                | Quebec                | Canada       |  46.1877  |  -74.6099   |   nan | http://en.wikipedia.org/wiki/Circuit_Mont-Tremblant                     |\n| 52 |          53 | essarts        | Rouen-Les-Essarts                     | Rouen                 | France       |  49.3306  |    1.00458  |   nan | http://en.wikipedia.org/wiki/Rouen-Les-Essarts                          |\n| 53 |          54 | lemans         | Le Mans                               | Le Mans               | France       |  47.95    |    0.224231 |   nan | http://en.wikipedia.org/wiki/Circuit_de_la_Sarthe#Bugatti_Circuit       |\n| 54 |          55 | reims          | Reims-Gueux                           | Reims                 | France       |  49.2542  |    3.93083  |   nan | http://en.wikipedia.org/wiki/Reims-Gueux                                |\n| 55 |          56 | george         | Prince George Circuit                 | Eastern Cape Province | South Africa | -33.0486  |   27.8736   |   nan | http://en.wikipedia.org/wiki/Prince_George_Circuit                      |\n| 56 |          57 | zeltweg        | Zeltweg                               | Styria                | Austria      |  47.2039  |   14.7478   |   nan | http://en.wikipedia.org/wiki/Zeltweg_Airfield                           |\n| 57 |          58 | aintree        | Aintree                               | Liverpool             | UK           |  53.4769  |   -2.94056  |   nan | http://en.wikipedia.org/wiki/Aintree_Motor_Racing_Circuit               |\n| 58 |          59 | boavista       | Circuito da Boavista                  | Oporto                | Portugal     |  41.1705  |   -8.67325  |   nan | http://en.wikipedia.org/wiki/Circuito_da_Boavista                       |\n| 59 |          60 | riverside      | Riverside International Raceway       | California            | USA          |  33.937   | -117.273    |   nan | http://en.wikipedia.org/wiki/Riverside_International_Raceway            |\n| 60 |          61 | avus           | AVUS                                  | Berlin                | Germany      |  52.4806  |   13.2514   |   nan | http://en.wikipedia.org/wiki/AVUS                                       |\n| 61 |          62 | monsanto       | Monsanto Park Circuit                 | Lisbon                | Portugal     |  38.7197  |   -9.20306  |   nan | http://en.wikipedia.org/wiki/Monsanto_Park_Circuit                      |\n| 62 |          63 | sebring        | Sebring International Raceway         | Florida               | USA          |  27.4547  |  -81.3483   |   nan | http://en.wikipedia.org/wiki/Sebring_Raceway                            |\n| 63 |          64 | ain-diab       | Ain Diab                              | Casablanca            | Morocco      |  33.5786  |   -7.6875   |   nan | http://en.wikipedia.org/wiki/Ain-Diab_Circuit                           |\n| 64 |          65 | pescara        | Pescara Circuit                       | Pescara               | Italy        |  42.475   |   14.1508   |   nan | http://en.wikipedia.org/wiki/Pescara_Circuit                            |\n| 65 |          66 | bremgarten     | Circuit Bremgarten                    | Bern                  | Switzerland  |  46.9589  |    7.40194  |   nan | http://en.wikipedia.org/wiki/Circuit_Bremgarten                         |\n| 66 |          67 | pedralbes      | Circuit de Pedralbes                  | Barcelona             | Spain        |  41.3903  |    2.11667  |   nan | http://en.wikipedia.org/wiki/Pedralbes_Circuit                          |\n| 67 |          68 | buddh          | Buddh International Circuit           | Uttar Pradesh         | India        |  28.3487  |   77.5331   |   nan | http://en.wikipedia.org/wiki/Buddh_International_Circuit                |\n| 68 |          69 | americas       | Circuit of the Americas               | Austin                | USA          |  30.1328  |  -97.6411   |   nan | http://en.wikipedia.org/wiki/Circuit_of_the_Americas                    |\n| 69 |          70 | red_bull_ring  | Red Bull Ring                         | Spielburg             | Austria      |  47.2197  |   14.7647   |   nan | http://en.wikipedia.org/wiki/Red_Bull_Ring                              |\n| 70 |          71 | sochi          | Sochi Autodrom                        | Sochi                 | Russia       |  43.4057  |   39.9578   |   nan | http://en.wikipedia.org/wiki/Sochi_Autodrom                             |\n| 71 |          72 | port_imperial  | Port Imperial Street Circuit          | New Jersey            | USA          |  40.7769  |  -74.0111   |   nan | http://en.wikipedia.org/wiki/Port_Imperial_Street_Circuit               |\n| 72 |          73 | BAK            | Baku City Circuit                     | Baku                  | Azerbaijan   |  40.3725  |   49.8533   |   nan | http://en.wikipedia.org/wiki/Baku_City_Circuit                          |\n\nTable: races - 40 rows | Row 12: found via circuitid | Row 30: found via circuitid | Row 47: found via circuitid | Row 55: found via circuitid | Row 66: found via circuitid | Row 73: found via circuitid | Row 81: found via circuitid | Row 82: found via circuitid | Row 84: found via circuitid | Row 85: found via circuitid | Row 87: found via circuitid | Row 88: found via circuitid | Row 90: found via circuitid | Row 91: found via circuitid | Row 93: found via circuitid | Row 94: found via circuitid | Row 96: found via circuitid | Row 97: found via circuitid | Row 99: found via circuitid | Row 100: found via circuitid | Row 102: found via circuitid | Row 103: found via circuitid | Row 105: found via circuitid | Row 106: found via circuitid | Row 108: found via circuitid | Row 109: found via circuitid | Row 111: found via circuitid | Row 112: found via circuitid | Row 114: found via circuitid | Row 115: found via circuitid | Row 117: found via circuitid | Row 118: found via circuitid | Row 120: found via circuitid | Row 121: found via circuitid | Row 123: found via circuitid | Row 124: found via circuitid | Row 126: found via circuitid | Row 128: found via circuitid | Row 129: found via circuitid | Row 131: found via circuitid\n|     |   raceid |   year |   round |   circuitid | name                  | date       | time     | url                                                     |\n|----:|---------:|-------:|--------:|------------:|:----------------------|:-----------|:---------|:--------------------------------------------------------|\n|  12 |       13 |   2009 |      13 |          14 | Italian Grand Prix    | 2009-09-13 | 12:00:00 | http://en.wikipedia.org/wiki/2009_Italian_Grand_Prix    |\n|  30 |       31 |   2008 |      14 |          14 | Italian Grand Prix    | 2008-09-14 | 12:00:00 | http://en.wikipedia.org/wiki/2008_Italian_Grand_Prix    |\n|  47 |       48 |   2007 |      13 |          14 | Italian Grand Prix    | 2007-09-09 | 12:00:00 | http://en.wikipedia.org/wiki/2007_Italian_Grand_Prix    |\n|  55 |       56 |   2006 |       4 |          21 | San Marino Grand Prix | 2006-04-23 | 14:00:00 | http://en.wikipedia.org/wiki/2006_San_Marino_Grand_Prix |\n|  66 |       67 |   2006 |      15 |          14 | Italian Grand Prix    | 2006-09-10 | 14:00:00 | http://en.wikipedia.org/wiki/2006_Italian_Grand_Prix    |\n|  73 |       74 |   2005 |       4 |          21 | San Marino Grand Prix | 2005-04-24 | 14:00:00 | http://en.wikipedia.org/wiki/2005_San_Marino_Grand_Prix |\n|  81 |       85 |   2005 |      15 |          14 | Italian Grand Prix    | 2005-09-04 | 14:00:00 | http://en.wikipedia.org/wiki/2005_Italian_Grand_Prix    |\n|  82 |       93 |   2004 |       4 |          21 | San Marino Grand Prix | 2004-04-25 | nan      | http://en.wikipedia.org/wiki/2004_San_Marino_Grand_Prix |\n|  84 |      104 |   2004 |      15 |          14 | Italian Grand Prix    | 2004-09-12 | nan      | http://en.wikipedia.org/wiki/2004_Italian_Grand_Prix    |\n|  85 |      111 |   2003 |       4 |          21 | San Marino Grand Prix | 2003-04-20 | nan      | http://en.wikipedia.org/wiki/2003_San_Marino_Grand_Prix |\n|  87 |      121 |   2003 |      14 |          14 | Italian Grand Prix    | 2003-09-14 | nan      | http://en.wikipedia.org/wiki/2003_Italian_Grand_Prix    |\n|  88 |      127 |   2002 |       4 |          21 | San Marino Grand Prix | 2002-04-14 | nan      | http://en.wikipedia.org/wiki/2002_San_Marino_Grand_Prix |\n|  90 |      138 |   2002 |      15 |          14 | Italian Grand Prix    | 2002-09-15 | nan      | http://en.wikipedia.org/wiki/2002_Italian_Grand_Prix    |\n|  91 |      144 |   2001 |       4 |          21 | San Marino Grand Prix | 2001-04-15 | nan      | http://en.wikipedia.org/wiki/2001_San_Marino_Grand_Prix |\n|  93 |      155 |   2001 |      15 |          14 | Italian Grand Prix    | 2001-09-16 | nan      | http://en.wikipedia.org/wiki/2001_Italian_Grand_Prix    |\n|  94 |      160 |   2000 |       3 |          21 | San Marino Grand Prix | 2000-04-09 | nan      | http://en.wikipedia.org/wiki/2000_San_Marino_Grand_Prix |\n|  96 |      171 |   2000 |      14 |          14 | Italian Grand Prix    | 2000-09-10 | nan      | http://en.wikipedia.org/wiki/2000_Italian_Grand_Prix    |\n|  97 |      177 |   1999 |       3 |          21 | San Marino Grand Prix | 1999-05-02 | nan      | http://en.wikipedia.org/wiki/1999_San_Marino_Grand_Prix |\n|  99 |      187 |   1999 |      13 |          14 | Italian Grand Prix    | 1999-09-12 | nan      | http://en.wikipedia.org/wiki/1999_Italian_Grand_Prix    |\n| 100 |      194 |   1998 |       4 |          21 | San Marino Grand Prix | 1998-04-26 | nan      | http://en.wikipedia.org/wiki/1998_San_Marino_Grand_Prix |\n| 102 |      204 |   1998 |      14 |          14 | Italian Grand Prix    | 1998-09-13 | nan      | http://en.wikipedia.org/wiki/1998_Italian_Grand_Prix    |\n| 103 |      210 |   1997 |       4 |          21 | San Marino Grand Prix | 1997-04-27 | nan      | http://en.wikipedia.org/wiki/1997_San_Marino_Grand_Prix |\n| 105 |      219 |   1997 |      13 |          14 | Italian Grand Prix    | 1997-09-07 | nan      | http://en.wikipedia.org/wiki/1997_Italian_Grand_Prix    |\n| 106 |      228 |   1996 |       5 |          21 | San Marino Grand Prix | 1996-05-05 | nan      | http://en.wikipedia.org/wiki/1996_San_Marino_Grand_Prix |\n| 108 |      237 |   1996 |      14 |          14 | Italian Grand Prix    | 1996-09-08 | nan      | http://en.wikipedia.org/wiki/1996_Italian_Grand_Prix    |\n| 109 |      242 |   1995 |       3 |          21 | San Marino Grand Prix | 1995-04-30 | nan      | http://en.wikipedia.org/wiki/1995_San_Marino_Grand_Prix |\n| 111 |      251 |   1995 |      12 |          14 | Italian Grand Prix    | 1995-09-10 | nan      | http://en.wikipedia.org/wiki/1995_Italian_Grand_Prix    |\n| 112 |      259 |   1994 |       3 |          21 | San Marino Grand Prix | 1994-05-01 | nan      | http://en.wikipedia.org/wiki/1994_San_Marino_Grand_Prix |\n| 114 |      268 |   1994 |      12 |          14 | Italian Grand Prix    | 1994-09-11 | nan      | http://en.wikipedia.org/wiki/1994_Italian_Grand_Prix    |\n| 115 |      276 |   1993 |       4 |          21 | San Marino Grand Prix | 1993-04-25 | nan      | http://en.wikipedia.org/wiki/1993_San_Marino_Grand_Prix |\n| 117 |      285 |   1993 |      13 |          14 | Italian Grand Prix    | 1993-09-12 | nan      | http://en.wikipedia.org/wiki/1993_Italian_Grand_Prix    |\n| 118 |      293 |   1992 |       5 |          21 | San Marino Grand Prix | 1992-05-17 | nan      | http://en.wikipedia.org/wiki/1992_San_Marino_Grand_Prix |\n| 120 |      301 |   1992 |      13 |          14 | Italian Grand Prix    | 1992-09-13 | nan      | http://en.wikipedia.org/wiki/1992_Italian_Grand_Prix    |\n| 121 |      307 |   1991 |       3 |          21 | San Marino Grand Prix | 1991-04-28 | nan      | http://en.wikipedia.org/wiki/1991_San_Marino_Grand_Prix |\n| 123 |      316 |   1991 |      12 |          14 | Italian Grand Prix    | 1991-09-08 | nan      | http://en.wikipedia.org/wiki/1991_Italian_Grand_Prix    |\n| 124 |      323 |   1990 |       3 |          21 | San Marino Grand Prix | 1990-05-13 | nan      | http://en.wikipedia.org/wiki/1990_San_Marino_Grand_Prix |\n| 126 |      332 |   1990 |      12 |          14 | Italian Grand Prix    | 1990-09-09 | nan      | http://en.wikipedia.org/wiki/1990_Italian_Grand_Prix    |\n| 128 |      350 |   2010 |      14 |          14 | Italian Grand Prix    | 2010-09-12 | 12:00:00 | http://en.wikipedia.org/wiki/2010_Italian_Grand_Prix    |\n| 129 |      357 |   1989 |       2 |          21 | San Marino Grand Prix | 1989-04-23 | nan      | http://en.wikipedia.org/wiki/1989_San_Marino_Grand_Prix |\n| 131 |      367 |   1989 |      12 |          14 | Italian Grand Prix    | 1989-09-10 | nan      | http://en.wikipedia.org/wiki/1989_Italian_Grand_Prix    |\n\nTable: results - 72 rows | Row 6: found via constructorid | Row 7: found via constructorid | Row 12: found via constructorid | Row 19: found via constructorid | Row 22: found via constructorid | Row 39: found via constructorid | Row 40: found via constructorid | Row 43: found via constructorid | Row 44: found via constructorid | Row 45: found via constructorid | Row 58: found via constructorid | Row 65: found via constructorid | Row 66: found via constructorid | Row 67: found via constructorid | Row 77: found via constructorid | Row 79: found via constructorid | Row 89: found via constructorid | Row 90: found via constructorid | Row 97: found via constructorid | Row 99: found via constructorid | Row 101: found via constructorid | Row 105: found via constructorid | Row 109: found via constructorid | Row 111: found via constructorid | Row 113: found via constructorid | Row 114: found via constructorid | Row 118: found via constructorid | Row 124: found via constructorid | Row 125: found via constructorid | Row 126: found via constructorid | Row 127: found via constructorid | Row 128: found via constructorid | Row 129: found via constructorid | Row 137: found via constructorid | Row 141: found via constructorid | Row 143: found via constructorid | Row 144: found via constructorid | Row 146: found via constructorid | Row 149: found via constructorid | Row 150: found via constructorid | Row 157: found via constructorid | Row 160: found via constructorid | Row 164: found via constructorid | Row 165: found via constructorid | Row 168: found via constructorid | Row 170: found via constructorid | Row 171: found via constructorid | Row 196: found via constructorid | Row 205: found via constructorid | Row 208: found via constructorid | Row 218: found via constructorid | Row 226: found via constructorid | Row 228: found via constructorid | Row 230: found via constructorid | Row 232: found via constructorid | Row 235: found via constructorid | Row 238: found via constructorid | Row 250: found via constructorid | Row 255: found via constructorid | Row 266: found via constructorid | Row 269: found via constructorid | Row 294: found via constructorid | Row 304: found via constructorid | Row 306: found via constructorid | Row 308: found via constructorid | Row 312: found via constructorid | Row 316: found via constructorid | Row 317: found via constructorid | Row 318: found via constructorid | Row 319: found via constructorid | Row 324: found via constructorid | Row 334: found via constructorid\n|     |   resultid |   raceid |   driverid |   constructorid |   number |   grid |   position | positiontext   |   positionorder |   points |   laps | time        |   milliseconds |   fastestlap |   rank | fastestlaptime   |   fastestlapspeed |   statusid |\n|----:|-----------:|---------:|-----------:|----------------:|---------:|-------:|-----------:|:---------------|----------------:|---------:|-------:|:------------|---------------:|-------------:|-------:|:-----------------|------------------:|-----------:|\n|   6 |          7 |       18 |          7 |               5 |       14 |     17 |          7 | 7              |               7 |      2   |     55 | nan         |  nan           |           22 |     12 | 1:29.534         |           213.224 |          5 |\n|   7 |          8 |       18 |          8 |               6 |        1 |     15 |          8 | 8              |               8 |      1   |     53 | nan         |  nan           |           20 |      4 | 1:27.903         |           217.18  |          5 |\n|  12 |         13 |       18 |         13 |               6 |        2 |      4 |        nan | R              |              13 |      0   |     29 | nan         |  nan           |           23 |      6 | 1:28.175         |           216.51  |          5 |\n|  19 |         20 |       18 |         20 |               5 |       15 |      9 |        nan | R              |              20 |      0   |      0 | nan         |  nan           |          nan |    nan | nan              |           nan     |          4 |\n|  22 |         23 |       19 |          8 |               6 |        1 |      2 |          1 | 1              |               1 |     10   |     56 | 1:31:18.555 |    5.47856e+06 |           37 |      2 | 1:35.405         |           209.158 |          1 |\n|  39 |         40 |       19 |         20 |               5 |       15 |     15 |        nan | R              |              18 |      0   |     39 | nan         |  nan           |           37 |     14 | 1:36.870         |           205.995 |          5 |\n|  40 |         41 |       19 |         13 |               6 |        2 |      1 |        nan | R              |              19 |      0   |     30 | nan         |  nan           |           15 |      5 | 1:35.914         |           208.048 |         20 |\n|  43 |         44 |       19 |          7 |               5 |       14 |     18 |        nan | R              |              22 |      0   |      0 | nan         |  nan           |          nan |    nan | nan              |           nan     |         20 |\n|  44 |         45 |       20 |         13 |               6 |        2 |      2 |          1 | 1              |               1 |     10   |     57 | 1:31:06.970 |    5.46697e+06 |           38 |      3 | 1:33.600         |           208.153 |          1 |\n|  45 |         46 |       20 |          8 |               6 |        1 |      4 |          2 | 2              |               2 |      8   |     57 | +3.339      |    5.47031e+06 |           35 |      4 | 1:33.709         |           207.911 |          1 |\n|  58 |         59 |       20 |          7 |               5 |       14 |     15 |         15 | 15             |              15 |      0   |     56 | nan         |  nan           |           33 |     15 | 1:35.333         |           204.369 |         11 |\n|  65 |         66 |       20 |         20 |               5 |       15 |     19 |        nan | R              |              22 |      0   |      0 | nan         |  nan           |          nan |    nan | nan              |           nan     |          5 |\n|  66 |         67 |       21 |          8 |               6 |        1 |      1 |          1 | 1              |               1 |     10   |     66 | 1:38:19.051 |    5.89905e+06 |           46 |      1 | 1:21.670         |           205.191 |          1 |\n|  67 |         68 |       21 |         13 |               6 |        2 |      3 |          2 | 2              |               2 |      8   |     66 | +3.228      |    5.90228e+06 |           45 |      2 | 1:21.801         |           204.863 |          1 |\n|  77 |        465 |       40 |         26 |               5 |       19 |     18 |          9 | 9              |               9 |      0   |     77 | nan         |  nan           |           73 |     10 | 1:16.867         |           156.426 |         11 |\n|  79 |        812 |       56 |         13 |               6 |        6 |      4 |          4 | 4              |               4 |      5   |     62 | +17.096     |    5.48358e+06 |           12 |     10 | 1:25.528         |           208.731 |          1 |\n|  89 |       1715 |      100 |         30 |               6 |        1 |      4 |          1 | 1              |               1 |     10   |     60 | 1:24:42.700 |    5.0827e+06  |           14 |      1 | 1:18.739         |           235.049 |          1 |\n|  90 |       1809 |      104 |         47 |              18 |       21 |     19 |         15 | 15             |              15 |      0   |     50 | nan         |  nan           |           31 |     18 | 1:26.356         |           241.497 |         13 |\n|  97 |       2689 |      147 |         30 |               6 |        1 |      2 |          1 | 1              |               1 |     10   |     78 | 1:47:22.561 |    6.44256e+06 |          nan |    nan | nan              |           nan     |          1 |\n|  99 |       2737 |      149 |         22 |               6 |        2 |      4 |          5 | 5              |               5 |      2   |     67 | +45.495     |    5.42822e+06 |          nan |    nan | nan              |           nan     |          1 |\n| 101 |       2789 |      151 |         21 |              22 |        7 |     19 |         13 | 13             |              13 |      0   |     58 | nan         |  nan           |          nan |    nan | nan              |           nan     |         12 |\n| 105 |       3048 |      163 |         60 |              18 |       21 |     21 |          8 | 8              |               8 |      0   |     65 | nan         |  nan           |          nan |    nan | nan              |           nan     |         12 |\n| 109 |       3370 |      178 |         30 |               6 |        3 |      2 |          1 | 1              |               1 |     10   |     78 | 1:49:31.812 |    6.57181e+06 |          nan |    nan | nan              |           nan     |          1 |\n| 111 |       3556 |      186 |         21 |              22 |        9 |     13 |         11 | 11             |              11 |      0   |     44 | +1:32.195   |    5.23525e+06 |          nan |    nan | nan              |           nan     |          1 |\n| 113 |       3835 |      199 |         21 |              22 |        5 |     10 |          5 | 5              |               5 |      2   |     59 | nan         |  nan           |          nan |    nan | nan              |           nan     |         11 |\n| 114 |       4095 |      211 |         30 |               6 |        5 |      2 |          1 | 1              |               1 |     10   |     62 | 2:00:05.654 |    7.20565e+06 |          nan |    nan | nan              |           nan     |          1 |\n| 118 |       4337 |      222 |         30 |               6 |        5 |      2 |          1 | 1              |               1 |     10   |     53 | 1:29:48.446 |    5.38845e+06 |          nan |    nan | nan              |           nan     |          1 |\n| 124 |       4733 |      240 |         69 |              18 |       24 |     18 |        nan | R              |              13 |      0   |     47 | nan         |  nan           |          nan |    nan | nan              |           nan     |          5 |\n| 125 |       4734 |      240 |         90 |              28 |       22 |     23 |        nan | R              |              14 |      0   |     47 | nan         |  nan           |          nan |    nan | nan              |           nan     |         20 |\n| 126 |       4825 |      244 |         30 |              22 |        1 |      2 |          1 | 1              |               1 |     10   |     78 | 1:53:11.258 |    6.79126e+06 |          nan |    nan | nan              |           nan     |          1 |\n| 127 |       4899 |      247 |         65 |              22 |        2 |      5 |          1 | 1              |               1 |     10   |     61 | 1:34:35.093 |    5.67509e+06 |          nan |    nan | nan              |           nan     |          1 |\n| 128 |       5196 |      259 |         78 |               6 |       27 |      6 |          2 | 2              |               2 |      6   |     58 | +54.942     |    5.36358e+06 |          nan |    nan | nan              |           nan     |          1 |\n| 129 |       5223 |      260 |         30 |              22 |        5 |      1 |          1 | 1              |               1 |     10   |     78 | 1:49:55.3   |    6.5953e+06  |          nan |    nan | nan              |           nan     |          1 |\n| 137 |       6319 |      299 |         94 |              35 |       22 |     26 |        nan | R              |              14 |      0   |     40 | nan         |  nan           |          nan |    nan | nan              |           nan     |          6 |\n| 141 |       6449 |      304 |         84 |              22 |       20 |      8 |          3 | 3              |               3 |      4   |     81 | +54.156     |    6.46894e+06 |          nan |    nan | nan              |           nan     |          1 |\n| 143 |       6540 |      306 |        142 |              42 |       31 |      0 |        nan | F              |              34 |      0   |      0 | nan         |  nan           |          nan |    nan | nan              |           nan     |         97 |\n| 144 |       6574 |      307 |        142 |              42 |       31 |      0 |        nan | F              |              34 |      0   |      0 | nan         |  nan           |          nan |    nan | nan              |           nan     |         97 |\n| 146 |       6767 |      313 |         81 |              18 |       24 |     19 |        nan | R              |              23 |      0   |     14 | nan         |  nan           |          nan |    nan | nan              |           nan     |         24 |\n| 149 |       7044 |      321 |        149 |              44 |       34 |      0 |        nan | F              |              33 |      0   |      0 | nan         |  nan           |          nan |    nan | nan              |           nan     |         97 |\n| 150 |       7104 |      323 |        139 |              35 |       21 |     21 |        nan | R              |              23 |      0   |      2 | nan         |  nan           |          nan |    nan | nan              |           nan     |         20 |\n| 157 |       7770 |       11 |         69 |               6 |        3 |     20 |         17 | 17             |              17 |      0   |     56 | nan         |  nan           |           52 |     18 | 1:40.590         |           193.939 |         11 |\n| 160 |       7886 |      356 |        110 |              35 |       22 |     15 |         13 | 13             |              13 |      0   |     57 | nan         |  nan           |          nan |    nan | nan              |           nan     |         14 |\n| 164 |       8095 |      361 |         65 |              22 |       20 |      0 |        nan | F              |              29 |      0   |      0 | nan         |  nan           |          nan |    nan | nan              |           nan     |         81 |\n| 165 |       8100 |      361 |        160 |              45 |       18 |      0 |        nan | F              |              34 |      0   |      0 | nan         |  nan           |          nan |    nan | nan              |           nan     |         97 |\n| 168 |       8402 |      369 |         78 |              45 |       17 |     11 |        nan | R              |              25 |      0   |      6 | nan         |  nan           |          nan |    nan | nan              |           nan     |         22 |\n| 170 |       8498 |      372 |        105 |               6 |       27 |      6 |          5 | 5              |               5 |      2   |     60 | +1:14.556   |    5.84141e+06 |          nan |    nan | nan              |           nan     |          1 |\n| 171 |       8530 |      373 |        145 |              22 |       19 |      4 |          6 | 6              |               6 |      1   |     59 | nan         |  nan           |          nan |    nan | nan              |           nan     |         11 |\n| 196 |      10308 |      439 |        163 |               6 |       28 |      6 |          2 | 2              |               2 |      6   |     60 | +13.416     |    5.8271e+06  |          nan |    nan | nan              |           nan     |          1 |\n| 205 |      10951 |      462 |        181 |              54 |        9 |     13 |        nan | R              |              14 |      0   |     33 | nan         |  nan           |          nan |    nan | nan              |           nan     |         47 |\n| 208 |      11089 |      467 |        181 |              54 |        9 |     20 |         10 | 10             |              10 |      0   |     75 | nan         |  nan           |          nan |    nan | nan              |           nan     |         12 |\n| 218 |      11696 |      488 |        203 |               6 |       27 |      2 |          1 | 1              |               1 |      9   |     76 | 1:54:23.38  |    6.86338e+06 |          nan |    nan | nan              |           nan     |          1 |\n| 226 |      12347 |      510 |        222 |               6 |        1 |      0 |        nan | F              |              26 |      0   |      0 | nan         |  nan           |          nan |    nan | nan              |           nan     |         81 |\n| 228 |      12368 |      511 |        158 |              45 |       31 |     16 |        nan | R              |              19 |      0   |     20 | nan         |  nan           |          nan |    nan | nan              |           nan     |         22 |\n| 230 |      12456 |      515 |        222 |               6 |       11 |      3 |          2 | 2              |               2 |      6   |     80 | +29.38      |    6.65478e+06 |          nan |    nan | nan              |           nan     |          1 |\n| 232 |      12536 |      518 |        222 |               6 |       11 |      1 |          1 | 1              |               1 |      9   |     76 | 1:55:22.48  |    6.92248e+06 |          nan |    nan | nan              |           nan     |          1 |\n| 235 |      12601 |      520 |        203 |               6 |       12 |     13 |         14 | 14             |              14 |      0   |     63 | nan         |  nan           |          nan |    nan | nan              |           nan     |         69 |\n| 238 |      12773 |      526 |        152 |              51 |       35 |     18 |        nan | R              |              24 |      0   |      0 | nan         |  nan           |          nan |    nan | nan              |           nan     |         20 |\n| 250 |      13861 |      565 |        182 |               6 |        1 |      1 |          1 | 1              |               1 |      9   |     78 | 1:59:51.47  |    7.19147e+06 |          nan |    nan | nan              |           nan     |          1 |\n| 255 |      14262 |      580 |        182 |               6 |       12 |      1 |          1 | 1              |               1 |      9   |     75 | 2:01:21.31  |    7.28131e+06 |          nan |    nan | nan              |           nan     |          1 |\n| 266 |      15023 |      607 |        235 |               6 |        8 |     11 |        nan | R              |              24 |      0   |      2 | nan         |  nan           |          nan |    nan | nan              |           nan     |          3 |\n| 269 |      15368 |      622 |        223 |               6 |        6 |      8 |          3 | 3              |               3 |      4   |     89 | nan         |  nan           |          nan |    nan | nan              |           nan     |         11 |\n| 294 |      17378 |      718 |        385 |               6 |        8 |      3 |          3 | 3              |               3 |      4   |     65 | +1:09.63    |    7.85995e+06 |          nan |    nan | nan              |           nan     |          1 |\n| 304 |      18644 |      772 |        403 |               6 |       23 |     10 |          9 | 9              |               9 |      0   |     15 | +7:45.5     |    8.9405e+06  |          nan |    nan | nan              |           nan     |          1 |\n| 306 |      18886 |      784 |        622 |             105 |       10 |     11 |          4 | 4              |               4 |      1.5 |     92 | nan         |  nan           |          nan |    nan | nan              |           nan     |         16 |\n| 308 |      19148 |      795 |        641 |               6 |       48 |      0 |        nan | W              |              15 |      0   |      0 | nan         |  nan           |          nan |    nan | nan              |           nan     |         54 |\n| 312 |      19486 |      811 |        670 |             105 |       28 |     16 |          3 | 3              |               3 |      4   |     35 | nan         |  nan           |          nan |    nan | nan              |           nan     |         11 |\n| 316 |      19736 |      821 |        647 |               6 |       15 |      2 |          1 | 1              |               1 |      9   |     85 | 2:46:11.0   |    9.971e+06   |          nan |    nan | nan              |           nan     |          1 |\n| 317 |      19966 |      830 |        723 |               6 |       91 |      8 |          6 | 6              |               6 |      0   |     19 | nan         |  nan           |          nan |    nan | nan              |           nan     |         11 |\n| 318 |      20127 |      837 |        780 |             105 |       30 |     11 |         10 | 10             |              10 |      0   |     29 | nan         |  nan           |          nan |    nan | nan              |           nan     |         16 |\n| 319 |      20259 |      793 |        632 |               6 |       48 |     15 |          8 | 8              |               8 |      0   |     86 | nan         |  nan           |          nan |    nan | nan              |           nan     |        111 |\n| 324 |      21021 |      851 |         13 |               6 |        6 |      4 |          6 | 6              |               6 |      8   |     70 | +1:23.176   |    6.48551e+06 |           61 |      1 | 1:23.415         |           189.073 |          1 |\n| 334 |      22198 |      903 |          4 |               6 |       14 |      5 |          3 | 3              |               3 |     15   |     54 | +23.604     |    5.63194e+06 |           48 |      4 | 1:42.081         |           192.235 |          1 |"}, "success": true}