{"input": {"tables_path": "/home/george/Documents/code/vkr/rustbench/tables-qa/set/Hockey/2/csv", "question_path": "/home/george/Documents/code/vkr/rustbench/tables-qa/set/Hockey/2/QA_english.json"}, "answers": "{\"answer\": 2}", "contexts": {"1-hop": "Table: awardsmisc - 84 rows | Row 0: found via award | Row 1: found via award | Row 2: found via award | Row 3: found via award | Row 4: found via award | Row 5: found via award | Row 6: found via award | Row 7: found via award | Row 8: found via award | Row 9: found via award | Row 10: found via award | Row 11: found via award | Row 12: found via award | Row 13: found via award | Row 14: found via award | Row 15: found via award | Row 16: found via award | Row 17: found via award | Row 18: found via award | Row 19: found via award | Row 20: found via award | Row 21: found via award | Row 22: found via award | Row 23: found via award | Row 24: found via award | Row 25: found via award | Row 26: found via award | Row 27: found via award | Row 28: found via award | Row 29: found via award | Row 30: found via award | Row 31: found via award | Row 32: found via award | Row 33: found via award | Row 34: found via award | Row 35: found via award | Row 36: found via award | Row 37: found via award | Row 38: found via award | Row 39: found via award | Row 40: found via award | Row 41: found via award | Row 42: found via award | Row 43: found via award | Row 44: found via award | Row 45: found via award | Row 46: found via award | Row 47: found via award | Row 48: found via award | Row 49: found via award | Row 50: found via award | Row 51: found via award | Row 52: found via award | Row 53: found via award | Row 54: found via award | Row 55: found via award | Row 56: found via award | Row 57: found via award | Row 58: found via award | Row 59: found via award | Row 60: found via award | Row 61: found via award | Row 62: found via award | Row 63: found via award | Row 64: found via award | Row 65: found via award | Row 66: found via award | Row 67: found via award | Row 68: found via award | Row 69: found via award | Row 70: found via award | Row 71: found via award | Row 72: found via award | Row 73: found via award | Row 74: found via award | Row 75: found via award | Row 76: found via award | Row 77: found via award | Row 78: found via award | Row 79: found via award | Row 80: found via award | Row 81: found via award | Row 82: found via award | Row 83: found via award\n|    | name                                  | id         | award   |   year | lgid   | note       |\n|---:|:--------------------------------------|:-----------|:--------|-------:|:-------|:-----------|\n|  0 | Al Arbour                             | arboual01  | Patrick |   1991 | NHL    | nan        |\n|  1 | Alex Delvecchio                       | delveal01  | Patrick |   1973 | NHL    | nan        |\n|  2 | Art Ross                              | rossar01   | Patrick |   1983 | NHL    | posthumous |\n|  3 | Bob Pulford                           | pulfobo01  | Patrick |   2010 | NHL    | nan        |\n|  4 | Bobby Clarke                          | clarkbo01  | Patrick |   1979 | NHL    | nan        |\n|  5 | Bobby Hull                            | hullbo01   | Patrick |   1968 | NHL    | nan        |\n|  6 | Bobby Orr                             | orrbo01    | Patrick |   1978 | NHL    | nan        |\n|  7 | Brian Leetch                          | leetcbr01  | Patrick |   2006 | NHL    | nan        |\n|  8 | Brian Mullen                          | mullebr01  | Patrick |   1994 | NHL    | nan        |\n|  9 | Bud Poile                             | poilebu01  | Patrick |   1988 | NHL    | nan        |\n| 10 | Cam Neely                             | neelyca01  | Patrick |   2009 | NHL    | nan        |\n| 11 | Cooney Weiland                        | weilaco01  | Patrick |   1971 | NHL    | nan        |\n| 12 | Craig Patrick                         | patricr01  | Patrick |   1999 | NHL    | nan        |\n| 13 | Dan Kelly                             | kellyda01  | Patrick |   1988 | NHL    | nan        |\n| 14 | Ed Jeremiah                           | jeremed01  | Patrick |   1968 | NHL    | posthumous |\n| 15 | Eddie Shore                           | shoreed01  | Patrick |   1969 | NHL    | nan        |\n| 16 | Emile Francis                         | francem01  | Patrick |   1981 | NHL    | nan        |\n| 17 | Frank Boucher                         | bouchfr01  | Patrick |   1992 | NHL    | nan        |\n| 18 | Frank Mathers                         | mathefr01  | Patrick |   1986 | NHL    | nan        |\n| 19 | Fred Shero                            | sherofr01  | Patrick |   1979 | NHL    | nan        |\n| 20 | Glen Sonmor                           | sonmogl01  | Patrick |   2005 | NHL    | nan        |\n| 21 | Gordie Howe                           | howego01   | Patrick |   1966 | NHL    | nan        |\n| 22 | Jack Adams                            | adamsja01  | Patrick |   1965 | NHL    | nan        |\n| 23 | Jack Riley                            | rileyja01  | Patrick |   1985 | NHL    | nan        |\n| 24 | Joe Mullen                            | mullejo01  | Patrick |   1994 | NHL    | nan        |\n| 25 | John Bucyk                            | bucykjo01  | Patrick |   1976 | NHL    | nan        |\n| 26 | John Davidson                         | davidjo01  | Patrick |   2003 | NHL    | nan        |\n| 27 | John Mariucci                         | mariujo01  | Patrick |   1976 | NHL    | nan        |\n| 28 | Keith Allen                           | allenke01  | Patrick |   1987 | NHL    | nan        |\n| 29 | Ken Morrow                            | morroke01  | Patrick |   1995 | NHL    | nan        |\n| 30 | Larry Pleau                           | pleaula01  | Patrick |   2001 | NHL    | nan        |\n| 31 | Lou Nanne                             | nannelo01  | Patrick |   1988 | NHL    | nan        |\n| 32 | Lynn Patrick                          | patrily01  | Patrick |   1988 | NHL    | posthumous |\n| 33 | Marcel Dionne                         | dionnma01  | Patrick |   2005 | NHL    | nan        |\n| 34 | Mario Lemieux                         | lemiema01  | Patrick |   1999 | NHL    | nan        |\n| 35 | Mark Johnson                          | johnsma02  | Patrick |   2010 | NHL    | nan        |\n| 36 | Mark Messier                          | messima01  | Patrick |   2008 | NHL    | nan        |\n| 37 | Max McNab                             | mcnabma01  | Patrick |   1997 | NHL    | nan        |\n| 38 | Mike Richter                          | richtmi01  | Patrick |   2008 | NHL    | nan        |\n| 39 | Milt Schmidt                          | schmimi01  | Patrick |   1995 | NHL    | nan        |\n| 40 | Murray Armstrong                      | armstmu01  | Patrick |   1976 | NHL    | nan        |\n| 41 | Murray Murdoch                        | murdomu01  | Patrick |   1973 | NHL    | nan        |\n| 42 | Neal Broten                           | brotene01  | Patrick |   1997 | NHL    | nan        |\n| 43 | Pat LaFontaine                        | lafonpa01  | Patrick |   1996 | NHL    | nan        |\n| 44 | Phil Esposito                         | esposph01  | Patrick |   1977 | NHL    | nan        |\n| 45 | Phil Housley                          | houslph01  | Patrick |   2007 | NHL    | nan        |\n| 46 | Raymond Bourque                       | bourqra01  | Patrick |   2002 | NHL    | nan        |\n| 47 | Red Berenson                          | berenre01  | Patrick |   2005 | NHL    | nan        |\n| 48 | Red Dutton                            | duttore01  | Patrick |   1992 | NHL    | nan        |\n| 49 | Reed Larson                           | larsore01  | Patrick |   2005 | NHL    | nan        |\n| 50 | Rod Gilbert                           | gilbero01  | Patrick |   1990 | NHL    | nan        |\n| 51 | Stan Mikita                           | mikitst01  | Patrick |   1975 | NHL    | nan        |\n| 52 | Steve Yzerman                         | yzermst01  | Patrick |   2005 | NHL    | nan        |\n| 53 | Ted Lindsay                           | lindste01  | Patrick |   2007 | NHL    | nan        |\n| 54 | Terry Sawchuk                         | sawchte01  | Patrick |   1970 | NHL    | posthumous |\n| 55 | Wayne Gretzky                         | gretzwa01  | Patrick |   1993 | NHL    | nan        |\n| 56 | Willie O'Ree                          | oreewi01   | Patrick |   2002 | NHL    | nan        |\n| 57 | 1960 U.S. Olympic Hockey Team         | nan        | Patrick |   2001 | NHL    | nan        |\n| 58 | 1998 U.S. Olympic Women's Hockey Team | nan        | Patrick |   1998 | NHL    | nan        |\n| 59 | Art Berglund                          | nan        | Patrick |   1991 | NHL    | nan        |\n| 60 | Arthur Wirtz                          | wirtzar01h | Patrick |   1984 | NHL    | nan        |\n| 61 | Bill Chadwick                         | chadwbi01h | Patrick |   1974 | NHL    | nan        |\n| 62 | Bill Cleary                           | nan        | Patrick |   1996 | NHL    | nan        |\n| 63 | Bill Torrey                           | torrebi01h | Patrick |   1982 | NHL    | nan        |\n| 64 | Bob Fleming                           | nan        | Patrick |   1994 | NHL    | nan        |\n| 65 | Bob Johnson                           | johnsbo02c | Patrick |   1987 | NHL    | nan        |\n| 66 | Bob Naegele                           | nan        | Patrick |   2007 | NHL    | nan        |\n| 67 | Brian Burke                           | nan        | Patrick |   2007 | NHL    | nan        |\n| 68 | Bruce McNall                          | nan        | Patrick |   1992 | NHL    | nan        |\n| 69 | Bruce Norris                          | norribr01h | Patrick |   1975 | NHL    | nan        |\n| 70 | Cammi Granato                         | nan        | Patrick |   2006 | NHL    | nan        |\n| 71 | Charles Adams                         | adamsch01h | Patrick |   1966 | NHL    | posthumous |\n| 72 | Charles L. Crovat                     | nan        | Patrick |   1973 | NHL    | posthumous |\n| 73 | Charles M. Schulz                     | nan        | Patrick |   1980 | NHL    | nan        |\n| 74 | Clarence Campbell                     | campbcl01h | Patrick |   1971 | NHL    | nan        |\n| 75 | Dave Andrews                          | nan        | Patrick |   2009 | NHL    | nan        |\n| 76 | David Poile                           | nan        | Patrick |   2000 | NHL    | nan        |\n| 77 | Donald Clark                          | nan        | Patrick |   1974 | NHL    | nan        |\n| 78 | Ed Snider                             | snideed01h | Patrick |   1979 | NHL    | nan        |\n| 79 | Fred Cusick                           | nan        | Patrick |   1987 | NHL    | nan        |\n| 80 | Gary Bettman                          | nan        | Patrick |   2000 | NHL    | nan        |\n| 81 | George Gund                           | nan        | Patrick |   1995 | NHL    | nan        |\n| 82 | George Leader                         | nan        | Patrick |   1975 | NHL    | nan        |\n| 83 | Gil Stein                             | nan        | Patrick |   1992 | NHL    | nan        |", "2-hop": "Table: awardsmisc - 84 rows | Row 0: found via award, id, lgid, year | Row 1: found via award, id, lgid, year | Row 2: found via award, id, lgid, year | Row 3: found via award, id, lgid, year | Row 4: found via award, id, lgid, year | Row 5: found via award, id, lgid, year | Row 6: found via award, id, lgid, year | Row 7: found via award, id, lgid, year | Row 8: found via award, id, lgid, year | Row 9: found via award, id, lgid, year | Row 10: found via award, id, lgid, year | Row 11: found via award, id, lgid, year | Row 12: found via award, id, lgid, year | Row 13: found via award, id, lgid, year | Row 14: found via award, id, lgid, year | Row 15: found via award, id, lgid, year | Row 16: found via award, id, lgid, year | Row 17: found via award, id, lgid, year | Row 18: found via award, id, lgid, year | Row 19: found via award, id, lgid, year | Row 20: found via award, id, lgid, year | Row 21: found via award, id, lgid, year | Row 22: found via award, id, lgid, year | Row 23: found via award, id, lgid, year | Row 24: found via award, id, lgid, year | Row 25: found via award, id, lgid, year | Row 26: found via award, id, lgid, year | Row 27: found via award, id, lgid, year | Row 28: found via award, id, lgid, year | Row 29: found via award, id, lgid, year | Row 30: found via award, id, lgid, year | Row 31: found via award, id, lgid, year | Row 32: found via award, id, lgid, year | Row 33: found via award, id, lgid, year | Row 34: found via award, id, lgid, year | Row 35: found via award, id, lgid, year | Row 36: found via award, id, lgid, year | Row 37: found via award, id, lgid, year | Row 38: found via award, id, lgid, year | Row 39: found via award, id, lgid, year | Row 40: found via award, id, lgid, year | Row 41: found via award, id, lgid, year | Row 42: found via award, id, lgid, year | Row 43: found via award, id, lgid, year | Row 44: found via award, id, lgid, year | Row 45: found via award, id, lgid, year | Row 46: found via award, id, lgid, year | Row 47: found via award, id, lgid, year | Row 48: found via award, id, lgid, year | Row 49: found via award, id, lgid, year | Row 50: found via award, id, lgid, year | Row 51: found via award, id, lgid, year | Row 52: found via award, id, lgid, year | Row 53: found via award, id, lgid, year | Row 54: found via award, id, lgid, year | Row 55: found via award, id, lgid, year | Row 56: found via award, id, lgid, year | Row 57: found via award, lgid, year | Row 58: found via award, lgid, year | Row 59: found via award, lgid, year | Row 60: found via award, id, lgid, year | Row 61: found via award, id, lgid, year | Row 62: found via award, lgid, year | Row 63: found via award, id, lgid, year | Row 64: found via award, lgid, year | Row 65: found via award, id, lgid, year | Row 66: found via award, lgid, year | Row 67: found via award, lgid, year | Row 68: found via award, lgid, year | Row 69: found via award, id, lgid, year | Row 70: found via award, lgid, year | Row 71: found via award, id, lgid, year | Row 72: found via award, lgid, year | Row 73: found via award, lgid, year | Row 74: found via award, id, lgid, year | Row 75: found via award, lgid, year | Row 76: found via award, lgid, year | Row 77: found via award, lgid, year | Row 78: found via award, id, lgid, year | Row 79: found via award, lgid, year | Row 80: found via award, lgid, year | Row 81: found via award, lgid, year | Row 82: found via award, lgid, year | Row 83: found via award, lgid, year\n|    | name                                  | id         | award   |   year | lgid   | note       |\n|---:|:--------------------------------------|:-----------|:--------|-------:|:-------|:-----------|\n|  0 | Al Arbour                             | arboual01  | Patrick |   1991 | NHL    | nan        |\n|  1 | Alex Delvecchio                       | delveal01  | Patrick |   1973 | NHL    | nan        |\n|  2 | Art Ross                              | rossar01   | Patrick |   1983 | NHL    | posthumous |\n|  3 | Bob Pulford                           | pulfobo01  | Patrick |   2010 | NHL    | nan        |\n|  4 | Bobby Clarke                          | clarkbo01  | Patrick |   1979 | NHL    | nan        |\n|  5 | Bobby Hull                            | hullbo01   | Patrick |   1968 | NHL    | nan        |\n|  6 | Bobby Orr                             | orrbo01    | Patrick |   1978 | NHL    | nan        |\n|  7 | Brian Leetch                          | leetcbr01  | Patrick |   2006 | NHL    | nan        |\n|  8 | Brian Mullen                          | mullebr01  | Patrick |   1994 | NHL    | nan        |\n|  9 | Bud Poile                             | poilebu01  | Patrick |   1988 | NHL    | nan        |\n| 10 | Cam Neely                             | neelyca01  | Patrick |   2009 | NHL    | nan        |\n| 11 | Cooney Weiland                        | weilaco01  | Patrick |   1971 | NHL    | nan        |\n| 12 | Craig Patrick                         | patricr01  | Patrick |   1999 | NHL    | nan        |\n| 13 | Dan Kelly                             | kellyda01  | Patrick |   1988 | NHL    | nan        |\n| 14 | Ed Jeremiah                           | jeremed01  | Patrick |   1968 | NHL    | posthumous |\n| 15 | Eddie Shore                           | shoreed01  | Patrick |   1969 | NHL    | nan        |\n| 16 | Emile Francis                         | francem01  | Patrick |   1981 | NHL    | nan        |\n| 17 | Frank Boucher                         | bouchfr01  | Patrick |   1992 | NHL    | nan        |\n| 18 | Frank Mathers                         | mathefr01  | Patrick |   1986 | NHL    | nan        |\n| 19 | Fred Shero                            | sherofr01  | Patrick |   1979 | NHL    | nan        |\n| 20 | Glen Sonmor                           | sonmogl01  | Patrick |   2005 | NHL    | nan        |\n| 21 | Gordie Howe                           | howego01   | Patrick |   1966 | NHL    | nan        |\n| 22 | Jack Adams                            | adamsja01  | Patrick |   1965 | NHL    | nan        |\n| 23 | Jack Riley                            | rileyja01  | Patrick |   1985 | NHL    | nan        |\n| 24 | Joe Mullen                            | mullejo01  | Patrick |   1994 | NHL    | nan        |\n| 25 | John Bucyk                            | bucykjo01  | Patrick |   1976 | NHL    | nan        |\n| 26 | John Davidson                         | davidjo01  | Patrick |   2003 | NHL    | nan        |\n| 27 | John Mariucci                         | mariujo01  | Patrick |   1976 | NHL    | nan        |\n| 28 | Keith Allen                           | allenke01  | Patrick |   1987 | NHL    | nan        |\n| 29 | Ken Morrow                            | morroke01  | Patrick |   1995 | NHL    | nan        |\n| 30 | Larry Pleau                           | pleaula01  | Patrick |   2001 | NHL    | nan        |\n| 31 | Lou Nanne                             | nannelo01  | Patrick |   1988 | NHL    | nan        |\n| 32 | Lynn Patrick                          | patrily01  | Patrick |   1988 | NHL    | posthumous |\n| 33 | Marcel Dionne                         | dionnma01  | Patrick |   2005 | NHL    | nan        |\n| 34 | Mario Lemieux                         | lemiema01  | Patrick |   1999 | NHL    | nan        |\n| 35 | Mark Johnson                          | johnsma02  | Patrick |   2010 | NHL    | nan        |\n| 36 | Mark Messier                          | messima01  | Patrick |   2008 | NHL    | nan        |\n| 37 | Max McNab                             | mcnabma01  | Patrick |   1997 | NHL    | nan        |\n| 38 | Mike Richter                          | richtmi01  | Patrick |   2008 | NHL    | nan        |\n| 39 | Milt Schmidt                          | schmimi01  | Patrick |   1995 | NHL    | nan        |\n| 40 | Murray Armstrong                      | armstmu01  | Patrick |   1976 | NHL    | nan        |\n| 41 | Murray Murdoch                        | murdomu01  | Patrick |   1973 | NHL    | nan        |\n| 42 | Neal Broten                           | brotene01  | Patrick |   1997 | NHL    | nan        |\n| 43 | Pat LaFontaine                        | lafonpa01  | Patrick |   1996 | NHL    | nan        |\n| 44 | Phil Esposito                         | esposph01  | Patrick |   1977 | NHL    | nan        |\n| 45 | Phil Housley                          | houslph01  | Patrick |   2007 | NHL    | nan        |\n| 46 | Raymond Bourque                       | bourqra01  | Patrick |   2002 | NHL    | nan        |\n| 47 | Red Berenson                          | berenre01  | Patrick |   2005 | NHL    | nan        |\n| 48 | Red Dutton                            | duttore01  | Patrick |   1992 | NHL    | nan        |\n| 49 | Reed Larson                           | larsore01  | Patrick |   2005 | NHL    | nan        |\n| 50 | Rod Gilbert                           | gilbero01  | Patrick |   1990 | NHL    | nan        |\n| 51 | Stan Mikita                           | mikitst01  | Patrick |   1975 | NHL    | nan        |\n| 52 | Steve Yzerman                         | yzermst01  | Patrick |   2005 | NHL    | nan        |\n| 53 | Ted Lindsay                           | lindste01  | Patrick |   2007 | NHL    | nan        |\n| 54 | Terry Sawchuk                         | sawchte01  | Patrick |   1970 | NHL    | posthumous |\n| 55 | Wayne Gretzky                         | gretzwa01  | Patrick |   1993 | NHL    | nan        |\n| 56 | Willie O'Ree                          | oreewi01   | Patrick |   2002 | NHL    | nan        |\n| 57 | 1960 U.S. Olympic Hockey Team         | nan        | Patrick |   2001 | NHL    | nan        |\n| 58 | 1998 U.S. Olympic Women's Hockey Team | nan        | Patrick |   1998 | NHL    | nan        |\n| 59 | Art Berglund                          | nan        | Patrick |   1991 | NHL    | nan        |\n| 60 | Arthur Wirtz                          | wirtzar01h | Patrick |   1984 | NHL    | nan        |\n| 61 | Bill Chadwick                         | chadwbi01h | Patrick |   1974 | NHL    | nan        |\n| 62 | Bill Cleary                           | nan        | Patrick |   1996 | NHL    | nan        |\n| 63 | Bill Torrey                           | torrebi01h | Patrick |   1982 | NHL    | nan        |\n| 64 | Bob Fleming                           | nan        | Patrick |   1994 | NHL    | nan        |\n| 65 | Bob Johnson                           | johnsbo02c | Patrick |   1987 | NHL    | nan        |\n| 66 | Bob Naegele                           | nan        | Patrick |   2007 | NHL    | nan        |\n| 67 | Brian Burke                           | nan        | Patrick |   2007 | NHL    | nan        |\n| 68 | Bruce McNall                          | nan        | Patrick |   1992 | NHL    | nan        |\n| 69 | Bruce Norris                          | norribr01h | Patrick |   1975 | NHL    | nan        |\n| 70 | Cammi Granato                         | nan        | Patrick |   2006 | NHL    | nan        |\n| 71 | Charles Adams                         | adamsch01h | Patrick |   1966 | NHL    | posthumous |\n| 72 | Charles L. Crovat                     | nan        | Patrick |   1973 | NHL    | posthumous |\n| 73 | Charles M. Schulz                     | nan        | Patrick |   1980 | NHL    | nan        |\n| 74 | Clarence Campbell                     | campbcl01h | Patrick |   1971 | NHL    | nan        |\n| 75 | Dave Andrews                          | nan        | Patrick |   2009 | NHL    | nan        |\n| 76 | David Poile                           | nan        | Patrick |   2000 | NHL    | nan        |\n| 77 | Donald Clark                          | nan        | Patrick |   1974 | NHL    | nan        |\n| 78 | Ed Snider                             | snideed01h | Patrick |   1979 | NHL    | nan        |\n| 79 | Fred Cusick                           | nan        | Patrick |   1987 | NHL    | nan        |\n| 80 | Gary Bettman                          | nan        | Patrick |   2000 | NHL    | nan        |\n| 81 | George Gund                           | nan        | Patrick |   1995 | NHL    | nan        |\n| 82 | George Leader                         | nan        | Patrick |   1975 | NHL    | nan        |\n| 83 | Gil Stein                             | nan        | Patrick |   1992 | NHL    | nan        |", "3-hop": "Table: awardsmisc - 84 rows | Row 0: found via award, id, lgid, year | Row 1: found via award, id, lgid, year | Row 2: found via award, id, lgid, year | Row 3: found via award, id, lgid, year | Row 4: found via award, id, lgid, year | Row 5: found via award, id, lgid, year | Row 6: found via award, id, lgid, year | Row 7: found via award, id, lgid, year | Row 8: found via award, id, lgid, year | Row 9: found via award, id, lgid, year | Row 10: found via award, id, lgid, year | Row 11: found via award, id, lgid, year | Row 12: found via award, id, lgid, year | Row 13: found via award, id, lgid, year | Row 14: found via award, id, lgid, year | Row 15: found via award, id, lgid, year | Row 16: found via award, id, lgid, year | Row 17: found via award, id, lgid, year | Row 18: found via award, id, lgid, year | Row 19: found via award, id, lgid, year | Row 20: found via award, id, lgid, year | Row 21: found via award, id, lgid, year | Row 22: found via award, id, lgid, year | Row 23: found via award, id, lgid, year | Row 24: found via award, id, lgid, year | Row 25: found via award, id, lgid, year | Row 26: found via award, id, lgid, year | Row 27: found via award, id, lgid, year | Row 28: found via award, id, lgid, year | Row 29: found via award, id, lgid, year | Row 30: found via award, id, lgid, year | Row 31: found via award, id, lgid, year | Row 32: found via award, id, lgid, year | Row 33: found via award, id, lgid, year | Row 34: found via award, id, lgid, year | Row 35: found via award, id, lgid, year | Row 36: found via award, id, lgid, year | Row 37: found via award, id, lgid, year | Row 38: found via award, id, lgid, year | Row 39: found via award, id, lgid, year | Row 40: found via award, id, lgid, year | Row 41: found via award, id, lgid, year | Row 42: found via award, id, lgid, year | Row 43: found via award, id, lgid, year | Row 44: found via award, id, lgid, year | Row 45: found via award, id, lgid, year | Row 46: found via award, id, lgid, year | Row 47: found via award, id, lgid, year | Row 48: found via award, id, lgid, year | Row 49: found via award, id, lgid, year | Row 50: found via award, id, lgid, year | Row 51: found via award, id, lgid, year | Row 52: found via award, id, lgid, year | Row 53: found via award, id, lgid, year | Row 54: found via award, id, lgid, year | Row 55: found via award, id, lgid, year | Row 56: found via award, id, lgid, year | Row 57: found via award, lgid, year | Row 58: found via award, lgid, year | Row 59: found via award, lgid, year | Row 60: found via award, id, lgid, year | Row 61: found via award, id, lgid, year | Row 62: found via award, lgid, year | Row 63: found via award, id, lgid, year | Row 64: found via award, lgid, year | Row 65: found via award, id, lgid, year | Row 66: found via award, lgid, year | Row 67: found via award, lgid, year | Row 68: found via award, lgid, year | Row 69: found via award, id, lgid, year | Row 70: found via award, lgid, year | Row 71: found via award, id, lgid, year | Row 72: found via award, lgid, year | Row 73: found via award, lgid, year | Row 74: found via award, id, lgid, year | Row 75: found via award, lgid, year | Row 76: found via award, lgid, year | Row 77: found via award, lgid, year | Row 78: found via award, id, lgid, year | Row 79: found via award, lgid, year | Row 80: found via award, lgid, year | Row 81: found via award, lgid, year | Row 82: found via award, lgid, year | Row 83: found via award, lgid, year\n|    | name                                  | id         | award   |   year | lgid   | note       |\n|---:|:--------------------------------------|:-----------|:--------|-------:|:-------|:-----------|\n|  0 | Al Arbour                             | arboual01  | Patrick |   1991 | NHL    | nan        |\n|  1 | Alex Delvecchio                       | delveal01  | Patrick |   1973 | NHL    | nan        |\n|  2 | Art Ross                              | rossar01   | Patrick |   1983 | NHL    | posthumous |\n|  3 | Bob Pulford                           | pulfobo01  | Patrick |   2010 | NHL    | nan        |\n|  4 | Bobby Clarke                          | clarkbo01  | Patrick |   1979 | NHL    | nan        |\n|  5 | Bobby Hull                            | hullbo01   | Patrick |   1968 | NHL    | nan        |\n|  6 | Bobby Orr                             | orrbo01    | Patrick |   1978 | NHL    | nan        |\n|  7 | Brian Leetch                          | leetcbr01  | Patrick |   2006 | NHL    | nan        |\n|  8 | Brian Mullen                          | mullebr01  | Patrick |   1994 | NHL    | nan        |\n|  9 | Bud Poile                             | poilebu01  | Patrick |   1988 | NHL    | nan        |\n| 10 | Cam Neely                             | neelyca01  | Patrick |   2009 | NHL    | nan        |\n| 11 | Cooney Weiland                        | weilaco01  | Patrick |   1971 | NHL    | nan        |\n| 12 | Craig Patrick                         | patricr01  | Patrick |   1999 | NHL    | nan        |\n| 13 | Dan Kelly                             | kellyda01  | Patrick |   1988 | NHL    | nan        |\n| 14 | Ed Jeremiah                           | jeremed01  | Patrick |   1968 | NHL    | posthumous |\n| 15 | Eddie Shore                           | shoreed01  | Patrick |   1969 | NHL    | nan        |\n| 16 | Emile Francis                         | francem01  | Patrick |   1981 | NHL    | nan        |\n| 17 | Frank Boucher                         | bouchfr01  | Patrick |   1992 | NHL    | nan        |\n| 18 | Frank Mathers                         | mathefr01  | Patrick |   1986 | NHL    | nan        |\n| 19 | Fred Shero                            | sherofr01  | Patrick |   1979 | NHL    | nan        |\n| 20 | Glen Sonmor                           | sonmogl01  | Patrick |   2005 | NHL    | nan        |\n| 21 | Gordie Howe                           | howego01   | Patrick |   1966 | NHL    | nan        |\n| 22 | Jack Adams                            | adamsja01  | Patrick |   1965 | NHL    | nan        |\n| 23 | Jack Riley                            | rileyja01  | Patrick |   1985 | NHL    | nan        |\n| 24 | Joe Mullen                            | mullejo01  | Patrick |   1994 | NHL    | nan        |\n| 25 | John Bucyk                            | bucykjo01  | Patrick |   1976 | NHL    | nan        |\n| 26 | John Davidson                         | davidjo01  | Patrick |   2003 | NHL    | nan        |\n| 27 | John Mariucci                         | mariujo01  | Patrick |   1976 | NHL    | nan        |\n| 28 | Keith Allen                           | allenke01  | Patrick |   1987 | NHL    | nan        |\n| 29 | Ken Morrow                            | morroke01  | Patrick |   1995 | NHL    | nan        |\n| 30 | Larry Pleau                           | pleaula01  | Patrick |   2001 | NHL    | nan        |\n| 31 | Lou Nanne                             | nannelo01  | Patrick |   1988 | NHL    | nan        |\n| 32 | Lynn Patrick                          | patrily01  | Patrick |   1988 | NHL    | posthumous |\n| 33 | Marcel Dionne                         | dionnma01  | Patrick |   2005 | NHL    | nan        |\n| 34 | Mario Lemieux                         | lemiema01  | Patrick |   1999 | NHL    | nan        |\n| 35 | Mark Johnson                          | johnsma02  | Patrick |   2010 | NHL    | nan        |\n| 36 | Mark Messier                          | messima01  | Patrick |   2008 | NHL    | nan        |\n| 37 | Max McNab                             | mcnabma01  | Patrick |   1997 | NHL    | nan        |\n| 38 | Mike Richter                          | richtmi01  | Patrick |   2008 | NHL    | nan        |\n| 39 | Milt Schmidt                          | schmimi01  | Patrick |   1995 | NHL    | nan        |\n| 40 | Murray Armstrong                      | armstmu01  | Patrick |   1976 | NHL    | nan        |\n| 41 | Murray Murdoch                        | murdomu01  | Patrick |   1973 | NHL    | nan        |\n| 42 | Neal Broten                           | brotene01  | Patrick |   1997 | NHL    | nan        |\n| 43 | Pat LaFontaine                        | lafonpa01  | Patrick |   1996 | NHL    | nan        |\n| 44 | Phil Esposito                         | esposph01  | Patrick |   1977 | NHL    | nan        |\n| 45 | Phil Housley                          | houslph01  | Patrick |   2007 | NHL    | nan        |\n| 46 | Raymond Bourque                       | bourqra01  | Patrick |   2002 | NHL    | nan        |\n| 47 | Red Berenson                          | berenre01  | Patrick |   2005 | NHL    | nan        |\n| 48 | Red Dutton                            | duttore01  | Patrick |   1992 | NHL    | nan        |\n| 49 | Reed Larson                           | larsore01  | Patrick |   2005 | NHL    | nan        |\n| 50 | Rod Gilbert                           | gilbero01  | Patrick |   1990 | NHL    | nan        |\n| 51 | Stan Mikita                           | mikitst01  | Patrick |   1975 | NHL    | nan        |\n| 52 | Steve Yzerman                         | yzermst01  | Patrick |   2005 | NHL    | nan        |\n| 53 | Ted Lindsay                           | lindste01  | Patrick |   2007 | NHL    | nan        |\n| 54 | Terry Sawchuk                         | sawchte01  | Patrick |   1970 | NHL    | posthumous |\n| 55 | Wayne Gretzky                         | gretzwa01  | Patrick |   1993 | NHL    | nan        |\n| 56 | Willie O'Ree                          | oreewi01   | Patrick |   2002 | NHL    | nan        |\n| 57 | 1960 U.S. Olympic Hockey Team         | nan        | Patrick |   2001 | NHL    | nan        |\n| 58 | 1998 U.S. Olympic Women's Hockey Team | nan        | Patrick |   1998 | NHL    | nan        |\n| 59 | Art Berglund                          | nan        | Patrick |   1991 | NHL    | nan        |\n| 60 | Arthur Wirtz                          | wirtzar01h | Patrick |   1984 | NHL    | nan        |\n| 61 | Bill Chadwick                         | chadwbi01h | Patrick |   1974 | NHL    | nan        |\n| 62 | Bill Cleary                           | nan        | Patrick |   1996 | NHL    | nan        |\n| 63 | Bill Torrey                           | torrebi01h | Patrick |   1982 | NHL    | nan        |\n| 64 | Bob Fleming                           | nan        | Patrick |   1994 | NHL    | nan        |\n| 65 | Bob Johnson                           | johnsbo02c | Patrick |   1987 | NHL    | nan        |\n| 66 | Bob Naegele                           | nan        | Patrick |   2007 | NHL    | nan        |\n| 67 | Brian Burke                           | nan        | Patrick |   2007 | NHL    | nan        |\n| 68 | Bruce McNall                          | nan        | Patrick |   1992 | NHL    | nan        |\n| 69 | Bruce Norris                          | norribr01h | Patrick |   1975 | NHL    | nan        |\n| 70 | Cammi Granato                         | nan        | Patrick |   2006 | NHL    | nan        |\n| 71 | Charles Adams                         | adamsch01h | Patrick |   1966 | NHL    | posthumous |\n| 72 | Charles L. Crovat                     | nan        | Patrick |   1973 | NHL    | posthumous |\n| 73 | Charles M. Schulz                     | nan        | Patrick |   1980 | NHL    | nan        |\n| 74 | Clarence Campbell                     | campbcl01h | Patrick |   1971 | NHL    | nan        |\n| 75 | Dave Andrews                          | nan        | Patrick |   2009 | NHL    | nan        |\n| 76 | David Poile                           | nan        | Patrick |   2000 | NHL    | nan        |\n| 77 | Donald Clark                          | nan        | Patrick |   1974 | NHL    | nan        |\n| 78 | Ed Snider                             | snideed01h | Patrick |   1979 | NHL    | nan        |\n| 79 | Fred Cusick                           | nan        | Patrick |   1987 | NHL    | nan        |\n| 80 | Gary Bettman                          | nan        | Patrick |   2000 | NHL    | nan        |\n| 81 | George Gund                           | nan        | Patrick |   1995 | NHL    | nan        |\n| 82 | George Leader                         | nan        | Patrick |   1975 | NHL    | nan        |\n| 83 | Gil Stein                             | nan        | Patrick |   1992 | NHL    | nan        |\n\nTable: teams - 56 rows | Row 0: found via lgid, year | Row 1: found via lgid, year | Row 2: found via lgid | Row 3: found via lgid, year | Row 4: found via lgid | Row 5: found via lgid | Row 6: found via lgid, year | Row 7: found via lgid, year | Row 8: found via lgid, year | Row 9: found via lgid, year | Row 10: found via lgid, year | Row 11: found via lgid, year | Row 12: found via lgid | Row 13: found via lgid, year | Row 14: found via lgid, year | Row 15: found via lgid, year | Row 16: found via lgid, year | Row 17: found via lgid, year | Row 18: found via lgid, year | Row 19: found via lgid | Row 20: found via lgid | Row 22: found via lgid, year | Row 23: found via lgid, year | Row 24: found via lgid, year | Row 25: found via lgid, year | Row 26: found via lgid, year | Row 27: found via lgid | Row 28: found via lgid, year | Row 29: found via lgid, year | Row 30: found via lgid | Row 31: found via lgid | Row 32: found via lgid | Row 33: found via lgid, year | Row 34: found via year | Row 35: found via lgid, year | Row 36: found via lgid | Row 37: found via lgid, year | Row 38: found via lgid, year | Row 39: found via lgid | Row 40: found via lgid | Row 41: found via lgid, year | Row 42: found via lgid, year | Row 43: found via lgid, year | Row 44: found via lgid, year | Row 46: found via lgid, year | Row 47: found via lgid, year | Row 48: found via lgid | Row 49: found via lgid | Row 50: found via lgid, year | Row 51: found via lgid | Row 52: found via lgid | Row 53: found via lgid | Row 54: found via lgid, year | Row 55: found via lgid | Row 56: found via lgid | Row 57: found via lgid\n|    |   year | lgid   | tmid   | franchid   | confid   | divid   |   rank | playoff   |   g |   w |   l |   t |   otl |   pts |   sow |   sol |   gf |   ga | name                    |   pim |   benchminor |   ppg |   ppc |   sha |   pkg |   pkc |   shf |\n|---:|-------:|:-------|:-------|:-----------|:---------|:--------|-------:|:----------|----:|----:|----:|----:|------:|------:|------:|------:|-----:|-----:|:------------------------|------:|-------------:|------:|------:|------:|------:|------:|------:|\n|  0 |   2005 | NHL    | NJD    | NJD        | EC       | AT      |      1 | CSF       |  82 |  46 |  27 | nan |     9 |   101 |     9 |     4 |  242 |  229 | New Jersey Devils       |   948 |           10 |    78 |   441 |     6 |    63 |   349 |     3 |\n|  1 |   2010 | NHL    | SJS    | SJS        | WC       | PC      |      1 | CF        |  82 |  48 |  25 | nan |     9 |   105 |     5 |     5 |  248 |  213 | San Jose Sharks         |   931 |           10 |    68 |   289 |     7 |    56 |   274 |     6 |\n|  2 |   1935 | NHL    | DET    | DET        | nan      | AM      |      1 | SC        |  48 |  24 |  16 |   8 |   nan |    56 |   nan |   nan |  124 |  103 | Detroit Red Wings       |   376 |          nan |   nan |   nan |   nan |   nan |   nan |   nan |\n|  3 |   2002 | NHL    | STL    | STL        | WC       | CE      |      2 | CQF       |  82 |  41 |  24 |  11 |     6 |    99 |   nan |   nan |  253 |  222 | St. Louis Blues         |  1618 |           16 |    80 |   391 |     7 |    71 |   389 |    11 |\n|  4 |   1948 | NHL    | BOS    | BOS        | nan      | nan     |      2 | SF        |  60 |  29 |  23 |   8 |   nan |    66 |   nan |   nan |  178 |  163 | Boston Bruins           |   434 |          nan |   nan |   nan |   nan |   nan |   nan |   nan |\n|  5 |   1926 | NHL    | CHI    | CHI        | nan      | AM      |      3 | QF        |  44 |  19 |  22 |   3 |   nan |    41 |   nan |   nan |  115 |  116 | Chicago Black Hawks     |   436 |          nan |   nan |   nan |   nan |   nan |   nan |   nan |\n|  6 |   2007 | NHL    | PHO    | PHO        | WC       | PC      |      4 | nan       |  82 |  38 |  37 | nan |     7 |    83 |     5 |     6 |  214 |  231 | Phoenix Coyotes         |  1193 |           18 |    63 |   339 |    12 |    64 |   332 |    11 |\n|  7 |   1993 | NHL    | FLO    | FLO        | EC       | AT      |      5 | nan       |  84 |  33 |  34 |  17 |   nan |    83 |   nan |   nan |  233 |  233 | Florida Panthers        |  1620 |            6 |    65 |   409 |    15 |    69 |   396 |     8 |\n|  8 |   2005 | NHL    | COL    | COL        | WC       | NW      |      2 | CSF       |  82 |  43 |  30 | nan |     9 |    95 |     3 |     6 |  283 |  257 | Colorado Avalanche      |  1178 |           26 |    89 |   473 |    12 |    69 |   448 |    11 |\n|  9 |   1988 | NHL    | NJD    | NJD        | WA       | PT      |      5 | nan       |  80 |  27 |  41 |  12 |   nan |    66 |   nan |   nan |  281 |  325 | New Jersey Devils       |  2499 |           24 |    85 |   466 |    15 |   115 |   467 |     7 |\n| 10 |   1999 | NHL    | ANA    | ANA        | WC       | PC      |      5 | nan       |  82 |  34 |  33 |  12 |     3 |    83 |   nan |   nan |  217 |  227 | Mighty Ducks of Anaheim |   926 |            8 |    55 |   332 |     8 |    62 |   296 |     4 |\n| 11 |   1984 | NHL    | TOR    | TOR        | CC       | NO      |      5 | nan       |  80 |  20 |  52 |   8 |   nan |    48 |   nan |   nan |  253 |  358 | Toronto Maple Leafs     |  1627 |           10 |    69 |   352 |    12 |    83 |   324 |    16 |\n| 12 |   1927 | NHL    | BOS    | BOS        | nan      | AM      |      1 | SF        |  44 |  20 |  13 |  11 |   nan |    51 |   nan |   nan |   77 |   70 | Boston Bruins           |   557 |          nan |   nan |   nan |   nan |   nan |   nan |   nan |\n| 13 |   1997 | NHL    | DET    | DET        | WC       | CE      |      2 | SC        |  82 |  44 |  23 |  15 |   nan |   103 |   nan |   nan |  250 |  196 | Detroit Red Wings       |  1346 |           12 |    67 |   381 |     7 |    51 |   376 |     8 |\n| 14 |   1983 | NHL    | CAL    | CAL        | CC       | SM      |      2 | DF        |  80 |  34 |  32 |  14 |   nan |    82 |   nan |   nan |  311 |  314 | Calgary Flames          |  1390 |            4 |    64 |   297 |    10 |    63 |   315 |    15 |\n| 15 |   1992 | NHL    | MNS    | DAL        | CC       | NO      |      5 | nan       |  84 |  36 |  38 |  10 |   nan |    82 |   nan |   nan |  272 |  293 | Minnesota North Stars   |  1885 |           14 |    85 |   445 |    17 |    81 |   455 |     9 |\n| 16 |   1982 | NHL    | QUE    | COL        | WA       | AD      |      4 | DSF       |  80 |  34 |  34 |  12 |   nan |    80 |   nan |   nan |  343 |  336 | Quebec Nordiques        |  1648 |           10 |    61 |   294 |     6 |    92 |   348 |     6 |\n| 17 |   1982 | NHL    | PIT    | PIT        | WA       | PT      |      6 | nan       |  80 |  18 |  53 |   9 |   nan |    45 |   nan |   nan |  257 |  394 | Pittsburgh Penguins     |  1859 |           20 |    81 |   358 |    15 |   110 |   396 |     3 |\n| 18 |   1991 | NHL    | QUE    | COL        | WA       | AD      |      5 | nan       |  80 |  20 |  48 |  12 |   nan |    52 |   nan |   nan |  255 |  318 | Quebec Nordiques        |  2044 |           26 |    66 |   385 |    14 |    87 |   421 |    11 |\n| 19 |   2011 | NHL    | NYI    | NYI        | EC       | AT      |      5 | nan       |  82 |  34 |  37 | nan |    11 |    79 |     7 |     4 |  203 |  255 | New York Islanders      |   763 |            8 |    45 |   243 |     5 |    46 |   236 |     4 |\n| 20 |   1934 | NHL    | MTM    | MTM        | nan      | CA      |      2 | SC        |  48 |  24 |  19 |   5 |   nan |    53 |   nan |   nan |  123 |   92 | Montreal Maroons        |   383 |          nan |   nan |   nan |   nan |   nan |   nan |   nan |\n| 22 |   1999 | NHL    | NYR    | NYR        | EC       | AT      |      4 | nan       |  82 |  29 |  38 |  12 |     3 |    73 |   nan |   nan |  218 |  246 | New York Rangers        |   916 |            4 |    55 |   325 |     9 |    49 |   292 |     5 |\n| 23 |   1993 | NHL    | CHI    | CHI        | WC       | CE      |      5 | CQF       |  84 |  39 |  36 |   9 |   nan |    87 |   nan |   nan |  254 |  240 | Chicago Blackhawks      |  2125 |           24 |    67 |   383 |    10 |    71 |   427 |    15 |\n| 24 |   1982 | NHL    | STL    | STL        | CC       | NO      |      4 | DSF       |  80 |  25 |  40 |  15 |   nan |    65 |   nan |   nan |  285 |  316 | St. Louis Blues         |  1281 |           12 |    67 |   316 |    12 |    63 |   336 |     9 |\n| 25 |   1984 | NHL    | VAN    | VAN        | CC       | SM      |      5 | nan       |  80 |  25 |  46 |   9 |   nan |    59 |   nan |   nan |  284 |  401 | Vancouver Canucks       |  1451 |           12 |    61 |   313 |    14 |    89 |   302 |     8 |\n| 26 |   2008 | NHL    | COL    | COL        | WC       | NW      |      5 | nan       |  82 |  32 |  45 | nan |     5 |    69 |     9 |     4 |  199 |  257 | Colorado Avalanche      |  1062 |           18 |    50 |   318 |     8 |    64 |   318 |     4 |\n| 27 |   1925 | NHL    | TRS    | TOR        | nan      | nan     |      6 | nan       |  36 |  12 |  21 |   3 |   nan |    27 |   nan |   nan |   92 |  114 | Toronto St. Patricks    |   325 |          nan |   nan |   nan |   nan |   nan |   nan |   nan |\n| 28 |   2007 | NHL    | VAN    | VAN        | WC       | NW      |      5 | nan       |  82 |  39 |  33 | nan |    10 |    88 |     6 |     9 |  213 |  215 | Vancouver Canucks       |  1474 |           16 |    63 |   369 |     7 |    64 |   368 |     8 |\n| 29 |   2003 | NHL    | NAS    | NAS        | WC       | CE      |      3 | CQF       |  82 |  38 |  29 |  11 |     4 |    91 |   nan |   nan |  216 |  217 | Nashville Predators     |  1360 |           28 |    72 |   428 |     8 |    64 |   351 |    14 |\n| 30 |   1921 | NHL    | TRS    | TOR        | nan      | nan     |      2 | SC        |  24 |  13 |  10 |   1 |   nan |    27 |   nan |   nan |   98 |   97 | Toronto St. Patricks    |   160 |          nan |   nan |   nan |   nan |   nan |   nan |   nan |\n| 31 |   1989 | NHL    | QUE    | COL        | WA       | AD      |      5 | nan       |  80 |  12 |  61 |   7 |   nan |    31 |   nan |   nan |  240 |  407 | Quebec Nordiques        |  2104 |           20 |    70 |   371 |    15 |    98 |   382 |     8 |\n| 32 |   1954 | NHL    | MTL    | MTL        | nan      | nan     |      2 | F         |  70 |  41 |  18 |  11 |   nan |    93 |   nan |   nan |  228 |  157 | Montreal Canadiens      |   890 |          nan |   nan |   nan |   nan |   nan |   nan |   nan |\n| 33 |   1974 | NHL    | WAS    | WAS        | WA       | NO      |      5 | nan       |  80 |   8 |  67 |   5 |   nan |    21 |   nan |   nan |  181 |  446 | Washington Capitals     |  1085 |           14 |    48 |   372 |    18 |    94 |   328 |     8 |\n| 34 |   1978 | WHA    | FIN    | FIN        | nan      | nan     |     10 | nan       |   1 |   0 |   1 |   0 |   nan |     0 |   nan |   nan |    4 |    8 | Finland                 |     2 |          nan |   nan |   nan |   nan |   nan |   nan |   nan |\n| 35 |   1995 | NHL    | MTL    | MTL        | EC       | NE      |      3 | CQF       |  82 |  40 |  32 |  10 |   nan |    90 |   nan |   nan |  265 |  248 | Montreal Canadiens      |  1847 |           34 |    77 |   405 |    11 |    68 |   382 |    15 |\n| 36 |   1954 | NHL    | TOR    | TOR        | nan      | nan     |      3 | SF        |  70 |  24 |  24 |  22 |   nan |    70 |   nan |   nan |  147 |  135 | Toronto Maple Leafs     |   990 |          nan |   nan |   nan |   nan |   nan |   nan |   nan |\n| 37 |   1992 | NHL    | NYI    | NYI        | WA       | PT      |      3 | CF        |  84 |  40 |  37 |   7 |   nan |    87 |   nan |   nan |  335 |  297 | New York Islanders      |  1701 |            4 |    90 |   416 |     8 |    77 |   375 |    12 |\n| 38 |   2006 | NHL    | COL    | COL        | WC       | NW      |      4 | nan       |  82 |  44 |  31 | nan |     7 |    95 |     5 |     4 |  272 |  251 | Colorado Avalanche      |   884 |           20 |    79 |   374 |     9 |    70 |   353 |     7 |\n| 39 |   1956 | NHL    | BOS    | BOS        | nan      | nan     |      3 | F         |  70 |  34 |  24 |  12 |   nan |    80 |   nan |   nan |  195 |  174 | Boston Bruins           |   978 |          nan |   nan |   nan |   nan |   nan |   nan |   nan |\n| 40 |   1944 | NHL    | CHI    | CHI        | nan      | nan     |      5 | nan       |  50 |  13 |  30 |   7 |   nan |    33 |   nan |   nan |  141 |  194 | Chicago Black Hawks     |   250 |          nan |   nan |   nan |   nan |   nan |   nan |   nan |\n| 41 |   1990 | NHL    | WIN    | PHO        | CC       | SM      |      5 | nan       |  80 |  26 |  43 |  11 |   nan |    63 |   nan |   nan |  260 |  288 | Winnipeg Jets           |  1675 |           10 |    74 |   381 |    12 |    57 |   351 |     8 |\n| 42 |   1974 | NHL    | NYI    | NYI        | CC       | PT      |      3 | SF        |  80 |  33 |  25 |  22 |   nan |    88 |   nan |   nan |  264 |  221 | New York Islanders      |  1116 |            2 |    51 |   273 |     7 |    55 |   340 |    11 |\n| 43 |   1977 | NHL    | NYI    | NYI        | CC       | PT      |      1 | QF        |  80 |  48 |  17 |  15 |   nan |   111 |   nan |   nan |  334 |  210 | New York Islanders      |   938 |            4 |    71 |   227 |     6 |    45 |   272 |     7 |\n| 44 |   1970 | NHL    | MTL    | MTL        | nan      | ED      |      3 | SC        |  78 |  42 |  23 |  13 |   nan |    97 |   nan |   nan |  291 |  216 | Montreal Canadiens      |  1271 |           10 |    71 |   286 |     6 |    49 |   319 |     8 |\n| 46 |   1994 | NHL    | BOS    | BOS        | EC       | NE      |      3 | CQF       |  48 |  27 |  18 |   3 |   nan |    57 |   nan |   nan |  150 |  127 | Boston Bruins           |   793 |            6 |    46 |   211 |     4 |    24 |   183 |     3 |\n| 47 |   2003 | NHL    | VAN    | VAN        | WC       | NW      |      1 | CQF       |  82 |  43 |  24 |  10 |     5 |   101 |   nan |   nan |  235 |  194 | Vancouver Canucks       |  1274 |           28 |    56 |   376 |     8 |    50 |   360 |     5 |\n| 48 |   1960 | NHL    | MTL    | MTL        | nan      | nan     |      1 | SF        |  70 |  41 |  19 |  10 |   nan |    92 |   nan |   nan |  254 |  188 | Montreal Canadiens      |   811 |          nan |   nan |   nan |   nan |   nan |   nan |   nan |\n| 49 |   1950 | NHL    | MTL    | MTL        | nan      | nan     |      3 | F         |  70 |  25 |  30 |  15 |   nan |    65 |   nan |   nan |  173 |  184 | Montreal Canadiens      |   835 |          nan |   nan |   nan |   nan |   nan |   nan |   nan |\n| 50 |   1992 | NHL    | HAR    | CAR        | WA       | AD      |      5 | nan       |  84 |  26 |  52 |   6 |   nan |    58 |   nan |   nan |  284 |  369 | Hartford Whalers        |  2354 |           24 |    78 |   444 |    14 |   107 |   493 |    12 |\n| 51 |   1967 | NHL    | MTL    | MTL        | nan      | ED      |      1 | SC        |  74 |  42 |  22 |  10 |   nan |    94 |   nan |   nan |  236 |  167 | Montreal Canadiens      |   698 |          nan |    50 |   245 |     3 |    34 |   205 |     7 |\n| 52 |   1953 | NHL    | DET    | DET        | nan      | nan     |      1 | SC        |  70 |  37 |  19 |  14 |   nan |    88 |   nan |   nan |  191 |  132 | Detroit Red Wings       |   814 |          nan |   nan |   nan |   nan |   nan |   nan |   nan |\n| 53 |   1962 | NHL    | TOR    | TOR        | nan      | nan     |      1 | SC        |  70 |  35 |  23 |  12 |   nan |    82 |   nan |   nan |  221 |  180 | Toronto Maple Leafs     |   816 |          nan |   nan |   nan |   nan |   nan |   nan |   nan |\n| 54 |   1979 | NHL    | VAN    | VAN        | CC       | SM      |      3 | PRE       |  80 |  27 |  37 |  16 |   nan |    70 |   nan |   nan |  256 |  281 | Vancouver Canucks       |  1808 |           16 |    53 |   312 |    12 |    69 |   282 |     2 |\n| 55 |   1926 | NHL    | BOS    | BOS        | nan      | AM      |      2 | F         |  44 |  21 |  20 |   3 |   nan |    45 |   nan |   nan |   97 |   89 | Boston Bruins           |   499 |          nan |   nan |   nan |   nan |   nan |   nan |   nan |\n| 56 |   1972 | NHL    | MNS    | DAL        | nan      | WD      |      3 | QF        |  78 |  37 |  30 |  11 |   nan |    85 |   nan |   nan |  254 |  230 | Minnesota North Stars   |   881 |            0 |    37 |   237 |     7 |    59 |   265 |     1 |\n| 57 |   1936 | NHL    | CHI    | CHI        | nan      | AM      |      4 | nan       |  48 |  14 |  27 |   7 |   nan |    35 |   nan |   nan |   99 |  131 | Chicago Black Hawks     |   291 |          nan |   nan |   nan |   nan |   nan |   nan |   nan |\n\nTable: master - 2 rows | Row 26: found via playerid | Row 71: found via playerid\n|    | playerid   | coachid    | hofid      | firstname   | lastname   |   namenote | namegiven      | namenick   |   height |   weight | shootcatch   | legendsid   |   ihdbid | hrefid    |   firstnhl |   lastnhl |   firstwha |   lastwha | pos   |   birthyear |   birthmon |   birthday | birthcountry   | birthstate   | birthcity    |   deathyear |   deathmon |   deathday |   deathcountry |   deathstate |   deathcity |\n|---:|:-----------|:-----------|:-----------|:------------|:-----------|-----------:|:---------------|:-----------|---------:|---------:|:-------------|:------------|---------:|:----------|-----------:|----------:|-----------:|----------:|:------|------------:|-----------:|-----------:|:---------------|:-------------|:-------------|------------:|-----------:|-----------:|---------------:|-------------:|------------:|\n| 26 | adamsja01  | adamsja01c | adamsja01h | Jack        | Adams      |        nan | John James     | Jolly Jack |       69 |      175 | R            | P195901     |    23806 | adamsja01 |       1917 |      1926 |        nan |       nan | C     |        1895 |          6 |         14 | Canada         | ON           | Fort William |        1968 |          5 |          1 |            nan |          nan |         nan |\n| 71 | allenke01  | allenke01c | allenke01h | Keith       | Allen      |        nan | Courtney Keith | Bingo      |       71 |      190 | L            | B199201     |    11406 | allenke01 |       1953 |      1954 |        nan |       nan | D     |        1923 |          8 |         21 | Canada         | SK           | Saskatoon    |         nan |        nan |        nan |            nan |          nan |         nan |"}, "success": true}